{
  "last_processed_id": "5XeFesFbtLpXzIVDNQP22n",
  "playlist_ids": {
    "My top tracks playlist": "4A5QHLGP8CkDpfYFepJCnA",
    "Bou & Hedex": "1M0dnD41tzKAJP8MWdPbVh",
    "Edmtrain's New Music Weekly": "2LVh8rHGisSis48ojsWeNO",
    "Itaewon Class OST": "1NbjaASwCH7qwDnPhyZdkY",
    "DJ Snake: The Collection": "5qHZqdZtMr4nIDghQxI6JE",
    "CRASSE 2023": "5hgoqWlooZ6XFqDZOJo2IG",
    "smile": "2hPBPP8P6CE01kaOdmxbwR",
    "ANIME OSTs - SALLE": "57waGJqM5SkJvThsIgo4Sb",
    "Spanish": "4IiQwUxjdZNEYKCJFreplY",
    "Gaming": "7mBkF44dY6wrM2AQix2iUW",
    "chill ost": "38FNzt5mCET2fVj21CdDdw",
    "Anime Lofi Playlist (for chill, study, sleep)": "1QcsybeUidDJIrPQTHS6dD",
    "zrce beach offical": "14sIOc9T19Z2xni1TciOCY",
    "\ud835\ude3d\ud835\ude47\ud835\ude3c\ud835\ude3e\ud835\ude46\ud835\ude47\ud835\ude44\ud835\ude4e\ud835\ude4f \ud835\ude4e\ud835\ude4a\ud835\ude47\ud835\ude3f\ud835\ude44\ud835\ude40\ud835\ude4d\ud835\ude4e": "3vCEPJUGs5mbfSlbqti8JV",
    "Favorites by DANTH": "5AwC6rIIFeODhamc0MhHgb",
    "Old Dubstep": "1pR69BGY57ZUos5oAvbn4b",
    "Hard": "7dAM36wQxa6lF0vjZl3Imu",
    "Raw/hardcore/uptempo": "3hEkOTn0XEQjra5xkwIHhf",
    "2000\u00b4s/2010\u2019s Bangers": "2mUdosd0n38TxzWgf0n2zA",
    "1AM Sound": "0VH8EKMTjT1EAAHF9D3i42",
    "Bass": "1xTEjSxY5OOaZShlPVyUeU",
    "FR": "4UZbEBv0zUaQu8GFmO0s1w",
    "Bootshaus Playlist": "7IDfxp4c7ub5T4fGv7SouH",
    "F1 Tracks: Aazar": "3HrMdJ1gDcYPI6Y4Qp7H7w",
    "Chillout - Lounge 2026": "2oTrz1dYy2l970ptp4KZta",
    "Fav of the moment": "5GU6et5YpMqHPDNDN2ZmXc",
    "TEAROUT 2026": "1F98zVV3OdmUap47TntXSq",
    "Crasse": "186pO2FJV0glGBYGf3aZt3",
    "80's / FRANCAIS & INTERNATIONAL": "6wcI7itkgmBhAqC9mFezCC",
    "BLACKLIST\u2716\ufe0f\u2716\ufe0f\u2716\ufe0fBOOTSHAUS": "7viSBZmJjNpqgw5tsmoE54",
    "Turbulence II Ultra Music Festival": "5EMV8YLCANkLaKdpLcWQh5",
    "NBA EXTRA ": "4CHtotRBKASLLDOtMiKIwJ",
    "Mes titres Shazam": "55jmRManBIhq9bBHhC1e9W",
    "WOB WOB WOB": "4aJPa4BYkONZ9f55Kc89uQ",
    "My Shazam Tracks": "0OapKmRl0HCMrXTl6gRZ8l",
    "NSD Mixes": "0KEWfN1VI1gQIuZwnnyZrV",
    "Europapark": "32T2hEJC89tA2BuuT1CLU6",
    "VOYD SELECTS PLAYLIST": "1ZcvpCN8zLSyw27vhpuD1O",
    "Best of Dubstep (TWINBOYS Takeover)": "3pZmNRGdF7pvYNBM15tYrv",
    "Confession Releases": "6isgOZHBBPbhQ7NqafDYT5",
    "Dessins anim\u00e9s 80's-90's-2000": "7C4KAuGcxxDkzuQxVFW6lw",
    "DnB": "0YirMk9RycI5X200Pd2wUf",
    "pablo escobar playlist": "2kbrYEpVNIOc6XKbh6Lt0v",
    "Secure The Baguette \ud83e\udd56": "3xYumRfkolghGAsa4dCjFr",
    "Flesh & Blood Playlist": "0HTAeh117DLCCpP6uSBGC6",
    "Electro x Progressive": "1T7jOgQTNIxtKJsunLZI4d",
    "Ete": "5x0PmamtmsCZlnSPaXUVEB",
    "NCS": "7rsV0MKU6HBjyBChlv1J7E",
    "80's": "5tZyEbUBn79FdjitroAJuh",
    "Rampage Drum&Bass": "3HNs6ZhyWva3XJRcWKlZA4",
    "Psy": "3jr0wFntayMZizR8rG9vDY",
    "Hardstyle(core)": "0xQwxQsAWwr0ILcJx8QVFG",
    "Old Skrillex": "3SGEJxaS8I0cLbsMkQzLDh",
    "Jersey": "0cKNKdOB0a0rNsXWjRrTD9",
    "Bassline UK": "2uHxEec00GfCy4kjTBf7eZ",
    "Rap": "6yuU4sTYegLOF5nTTt2Nig",
    "Banger": "7J8tCv1dMgSkwABKw0Su9R",
    "Trap/House": "3JBkszWW4Qzr0ubMO570Bh",
    "Favoris des radios": "5DTTdaRzj08WSL5r7Jrxqm",
    "Chill": "1KmzEruXyXfGOFwkojQwkN",
    "Dubstep": "5qrHrUcDEIJqKQZMynfniO",
    "EDM": "6aRAmS6dU34ZTRobfR1rNM",
    "Hip-Hop": "4x0rilTDTuKPwU91rBsOOP",
    "Riddim": "0uLLcrjdNIWCc9fyQVGW8T",
    "Rock": "1EHhBSzirqMIU4jvzcVoUZ",
    "Rap US": "3ZCCb3rT4003G09owBat5s",
    "Trap": "4bw5EGJDzpoGwxeJSEZxI7",
    "Drum and Bass": "1EHhBSzirqMIU4jvzcVoUZ",
    "Rap FR": "4x0rilTDTuKPwU91rBsOOP",
    "Hardstyle": "1TvmI1zbn2myUuAtRvJhMx",
    "Pop": "7znPiT8FaAjJtORdwV16lz",
    "Je ne dispose pas d'informations sur le titre et l'artiste.": "52qxtFCYyu2HiMxY58r8mb",
    "K-Pop": "39mg08Qxkbgrr6bbFmJP61",
    "Cumbia En El Monte": "0ZF6F7S9hiLUX7Aut6kLBD",
    "Cumbia Del Monte": "3E8xPAaGGJBgQX95CixmiB",
    "R&B": "5qUsRztPR9eLdPuL6TzxWo",
    "Classique": "1O45tW8PH9Mum4Pxsefx7U",
    "Je ne dispose pas d'informations suffisantes pour classer le titre.": "3lpEQPYtYr8LkhoWjtnArD",
    "Acoustique": "0O59w0o2MFNkc0jOLEqJt3",
    "Jazz": "5whynJxz6uG4r3DkzrAvof"
  },
  "classified_track_ids": [
    "36APkXtcen4Gt6Qp4Q5Otr",
    "1wAIjMwxC3KjRqHpaMkFvC",
    "55y30bh2ZUtzOXjWLxn7XT",
    "59NraMJsLaMCVtwXTSia8i",
    "5caEdTOBijqn114HuEsfJ6",
    "4E5P1XyAFtrjpiIxkydly4",
    "5Y4xZJ9IxClZIdgGXqxTfT",
    "075QgFfBAZe2TYET9pzX1R",
    "5B2KdpqWRwcnO2Cfxh7MSX",
    "6prNzDbevXmtrPzpzL7pFv",
    "1V6OSi0iI4rH93QvywhIUd",
    "6LNjBYBeSFpzVwM9cAvYMq",
    "02shCNmb6IvgB5jLqKjtkK",
    "0VjIjW4GlUZAMYd2vXMi3b",
    "1Szod3mLKHywl09AOy08Xc",
    "4q7dBdsALA5BSunzryc104",
    "4ZuuPLV4qYiznagLAFPHcW",
    "2dZAblgfUDNqDrTgjJIGsv",
    "7ikxeH5UEtVb5okhmgk60g",
    "56p7ocnzcI01YD4fJ2Av8U",
    "4q6yL426DmFKrUEUAIo8Yt",
    "251aCFbFK1f4Jkil96E5g1",
    "4Csunoy4CzQpywkB85V0Em",
    "6CvXSIz0xIOJvJem0MnyGl",
    "7hU3IHwjX150XLoTVmjD0q",
    "6nVyDjAhify9FGCF8TViJy",
    "1OFAYeaNrpEUaVntc3K6sp",
    "7p6GVOfojcPP4rVQ5SZNBY",
    "1iHQAF31WXoVG1ov7FLOsq",
    "2wm6DCnWcWwfsIl0LvWYZ8",
    "73vIOb4Q7YN6HeJTbscRx5",
    "49X0LAl6faAusYq02PRAY6",
    "7ycWLEP1GsNjVvcjawXz3z",
    "2dLClsgJ0NLuQry3sFKT9s",
    "5B5QxhlyrJ7UrI4CrkyS28",
    "7dFlym6ncWdS22IkKDtVmJ",
    "08lo8MO2RVzNRGO6da99RQ",
    "1nXrmQ6bWv3aZzR5KRnr2C",
    "47CK1SBOe7VR65GEmZmPjk",
    "1CWGkLldizcoXkthfhvNer",
    "6qONYDmRz1s7Msz0yVDHMB",
    "0xy1H3TnhU478kNe7E8Wxc",
    "61eyaitcIdl1jpnc6Kb8M3",
    "0vAXgfcS2hMaml2hAS1lgm",
    "2i90ZduBRD4ULeeF0DDLB6",
    "20FZrLl9zSbO9b3DhaqO6M",
    "5qGIfWDRdyO67LCTqA2sEn",
    "1JDIArrcepzWDTAWXdGYmP",
    "2Y0zwLevkIURWfu6AwI8qE",
    "6RH49kOurGNl02pT2iKOOp",
    "4IwAEVmGfA1gYYVFPtlXyi",
    "6aqy4ClnITiukw4WpIs1ln",
    "1coG30H5gED9tscKZookCC",
    "4ga4WvRNhMsIL38pkBbnIN",
    "7bpuBTsNwlWnBABYbCZAkN",
    "5H7m0gmdru2L8jleuoZ509",
    "6VRhkROS2SZHGlp0pxndbJ",
    "6qAcApH8obo8eqatCKUHd9",
    "05m4PsNFU52bDeIJmqHDYt",
    "0ApadYqa3GRQkJJ3E7pQDJ",
    "0KoiMHhqKLoL4xM54rcWYY",
    "4TKncDo2OglXAc3fHLJpXC",
    "57KrVuOJCmqLPMY6qaL6sW",
    "0ZKOjWGqV7vHl9WKOtDb5V",
    "15GnEZtHORosE5Eqq5oXrY",
    "1NuMliXjLTL0khzFsV9KCA",
    "2gY9nicNMXO20rvYDjhUxW",
    "7ANGoTYyFyT3pbdoioQ4h9",
    "1Q7NFNv0nC8avSFdZSYuf5",
    "5aXTfpNOqLj35ydEiLio67",
    "5xriTc82DdSAGToWcixBKf",
    "45Zx6DyqGKKmvfxfzRUtKl",
    "67kJ3o6PrkB9CetDTXQ1wR",
    "73JHauWZNH0eIl77GHT1zn",
    "3kX8csnbX6KWq0rR56hut5",
    "2BOKN1QLHtLQKacCIqsPhE",
    "4ZxOuNHhpyOj4gv52MtQpT",
    "3bUfnHiXtsfM2LWkkpXunI",
    "4uUG5RXrOk84mYEfFvj3cK",
    "1zG3vdLkyPZG9l9tWkSnVn",
    "7iS1Zyy6tZQZFAHbItdlfy",
    "3gGBT50XBgDkwfiyRbNbvY",
    "4xXAMzsWbr2XL3r9GIYS0g",
    "6UBVCjKn8zahjUqxopnKRD",
    "7G5NnTiw3AIaWOMuG51mzT",
    "3rgTS3933lMWoPiN6CW4qY",
    "3f4fc8c8unrQeKecmUPEDR",
    "2UECfYKvjLQ76a07fHPyFw",
    "5Oo9TVTEHd4wIX1gQFIVtd",
    "6iC7vapdKp0XlKhxOkp8QJ",
    "3ChIL36T1ae5J2ObXPAkWu",
    "5sysgWS6HwrfhHDnqMh27l",
    "5put6ich4wtW7pZXb1Jore",
    "0O986IRZ2rL3qGH5QiD4ZO",
    "5stp7wRju1bSPfpZWyhcbY",
    "0mlqPzYr22tXdpAX719vo4",
    "6GomT970rCOkKAyyrwJeZi",
    "1Yfr2DngmSx4brdd4nMTMV",
    "4FKRT4uPFx2L4exy9DCs1o",
    "0CehS6FAi1t1NAHvD0ianB",
    "7u6f174xl25TOBHA2HpFHO",
    "4jB8td98pbRVvTqtQ7I3MI",
    "2p9ejYHsE3AvXomYp34NWD",
    "0e5fRvipOUMMZzkmIOfZFH",
    "7bh4ulfXItdAbZJdMf4o5k",
    "45Vpdt9PsJUTyJ22qZGdSE",
    "06bbOz1a2idb6lYKTdNp96",
    "3ZFTkvIE7kyPt6Nu3PEa7V",
    "5LYRIyhmlrDAQsYdHEvP0f",
    "6gblTHN7eKFPvm4XxnYhl8",
    "2fd5w5z4JEeEickPRxlazj",
    "1HII0EIufOG0nGpWCQixbO",
    "4TBK6E1ERSKdIvD1jF4lt5",
    "2W9QUD9YJ4SERyzu25IwbU",
    "1T2yyYWmJ6kcHnEo18P1R3",
    "2DOc7EJutpU8OrBHV6RABG",
    "3pxSiLCw1zNGwxTFRDg99Q",
    "1PvOdn7lS3NFHVzUUWyxHB",
    "20on25jryn53hWghthWWW3",
    "6wZ3MptHGrbca0qdvcQsAR",
    "2cs9NbGdcutSqoy0SEmyuY",
    "0MsjqGeYAEPviKkIqFE0oy",
    "0x6GWeXWnoMmaKz7JNXgo1",
    "11Gypesywvx4AnUeYxeLaY",
    "0v1nobrUSVLIXrYaI4zwkw",
    "3FUZpoj9VV0sgc8RqbS3xQ",
    "7BhmwvCdQZNwuQXSHw5TzP",
    "7d8vBhH4KbxlS50SkNJPcK",
    "4OzMoyuArVMcDPW1WAenbJ",
    "2lKjHE4eSS4LAxan214Zpr",
    "1wJ2HKnLMpPZCpEpP630Jy",
    "3KvlsQNvQ8BLwJI7rkZCJp",
    "2CRz2pMU6A46P1cK30HQIT",
    "6JtoHj7XfP8pMkfmqMUW02",
    "74OedfkPbkzgb5SiZdThC3",
    "3oZoXyU0SkDldgS7AcN4y4",
    "0cADwMhiVVQpxwd2ShTleH",
    "3jbAzLVcHiI5hYSkcKe1Ty",
    "077AjPx334yMPROFwWZOUb",
    "1sN1DfP5uRzyWJi8b6fl0j",
    "3ROmQ4E9Nu0ZFTJVprp3Iu",
    "7KIbDUwumrpG5f30kEYW1v",
    "6nsKmSRCB5Au2OS5hBmSzf",
    "14M6BbiHt2w9KHVvoIUIUF",
    "2aI21FnmY7TJVKeMaoQZ0t",
    "5tz69p7tJuGPeMGwNTxYuV",
    "6Uj1ctrBOjOas8xZXGqKk4",
    "3J5AcWRzmgbq4svZt91l3e",
    "7GSaRgoagCXKcRzRWHqVWH",
    "40c3cZygoC1G0kuwg7eXjX",
    "7IA4vFk3nGuIL7aBPENCDa",
    "57Y16Yl1Ocu9WC837zQJz1",
    "3nFK1o9DPQMO83mEOnD214",
    "2il9NDpW87Hk2L9AjeDf8r",
    "26EWrD6O3kytoaCkiLeMzY",
    "7wGoVu4Dady5GV0Sv4UIsx",
    "0zZqNut5pMoIzufCjk1gWc",
    "0yuxvelKutObKMYDFijGWv",
    "10MLHY81Gd0yWbmX6jGWk4",
    "3OZFWBEmc901RScX4qD3JD",
    "1hChLdk0hBQbapbpVUVlNa",
    "4S69CXdHKfAD3kUhOhUEUI",
    "0FoSiffuAmaJ3VyPaebY6I",
    "5NfL27a8hse0etIIh7meNt",
    "4h9TZLHS7AZ30pt5c1o5Em",
    "720r2gUQv6U5qK39x91WMt",
    "0SqBlkhb8S17JgckYgTEbH",
    "6lBQ0SMCrJ7zy1LSCuXqwV",
    "2mEAc3LsnqpdKYcG9JDC9t",
    "7vWFaMq63AwkFDhS2OAg5u",
    "29vo9RUjxgZWXWGTpD8f4m",
    "0bhciG1J5Mn3aIfPjvHQIe",
    "7LWPWw7PtYHrDn194kNCPA",
    "3huLyepH2dViuUYLhMK1Iy",
    "4T9D8HvNML0kMwb0sRkSfJ",
    "7bP1p74oNpriSzLbnBVyDl",
    "6RcoVz80gcvv0sPjFapTCm",
    "7pS5VaWxJG8oYdL2c6tFGB",
    "2gmLcKpKY1quyatuJJLodB",
    "5KQn3B5Zvt6UtYKUuSAunX",
    "4ScwvBDTIAoDxtJtuOhurH",
    "07Sfoto6njtTUEDv6uEzLG",
    "7dRnTTSNr6IgsWf8DxIB1X",
    "0vOR6ILYOQKNaiXkgLgOZ7",
    "64vBCC1lpjEnF10CkDiDhv",
    "5fgT3t3IYunBVjKhEzJZv6",
    "4BVcmSJl06n5jjQsFi83yJ",
    "3bk11jHv8Uae1oWH5RqzUL",
    "3KliPMvk1EvFZu9cvkj8p1",
    "5F2lWCeBZMxpo6SG1Q3PlL",
    "1V0Zy7533bjXFSVtn3crzY",
    "0HXnDHMKc5VQNJ1xLHx9f8",
    "2TKSH16Qb0zVRcqrHc3D3h",
    "3DWjFSDEQ9IWz1mj449fB7",
    "0YzCQcsgj6KqwBHVx1mZrH",
    "0IoJNiqfeORsU6nMY9zC85",
    "5p6eRw87mlyRIKyA5GJX0D",
    "10ZAEeIWp9R4DEHk5QPsU0",
    "65uoaqX5qcjXZRheAj1qQT",
    "2lLJHufwVSJBTZkQRYmbGK",
    "2ncCB2DOggeQEDOb8HVKSy",
    "4FyesJzVpA39hbYvcseO2d",
    "6tJsWfCM0Bn7FKcHRDSgIZ",
    "6AT3n7L7hrQKVOwwYED9Sb",
    "0qWmdV9v1iY6cxLltyNGgs",
    "2PTvik6EqPAIYOclAB3SU8",
    "6s0OKvHJD0FEfp5CvJMhjm",
    "2gpWyfu7eZ01zzncHpxOtA",
    "7CzsHY7FBdH0qQ99I33Mos",
    "0WtM2NBVQNNJLh6scP13H8",
    "6jZhOffSvhyfei4PCfFUrI",
    "6TMsLIRJQ7LkfFY3g0DGKS",
    "78mlFc2LLiO7aeHnn1uCTR",
    "5Uj0VnayJKOuP9GmmDPNOx",
    "0k0GtcnyQLMiXrdEDbLXmJ",
    "2fGoErmzvqJ2OSCfsJ0KcG",
    "1g7j5AxiNKTGjryhFIlAsA",
    "32f2uFt0uqdrdtZC3jGejk",
    "2AlYncTpVHKwHb55F9lF6O",
    "6DuZiUskmmowv4zLdLfSxt",
    "2fHZHwEp6TP2ClC1S8ihVN",
    "6pwhTFf3rMUZTTzHKDDf2S",
    "1w3Q0fhdINUxWbmQX0mg1x",
    "7jrsF9BVnUislifkNsooPd",
    "6ptykWp2kljzQTS7orDQZw",
    "2NLuC1MWkEjB7TJtZ56fSg",
    "3KGU0C6v0sw4AsVhY6vZYY",
    "6F5Il2wmbdmhlbdBCdZ5Jy",
    "3wQpjllYtdQnOsYJKrc7Vh",
    "5TAtF576K1IU0LKlukhWtw",
    "1r3myKmjWoOqRip99CmSj1",
    "2ZQoWJMqk09UpAQt2Z712U",
    "7mZTno9Pj6JJPRjfmNQ21H",
    "5ygDXis42ncn6kYG14lEVG",
    "1hc1RAzkxc46Oe1FLt7b8H",
    "0BdpC4oQRY8qdGHCRGoxX9",
    "48Jf12YHPBCAfAzi255Rvr",
    "2pUsewGAEBAx0PXaK01ZoS",
    "2yHmIxXi48DFl6zQlIhEaj",
    "60lP1bVGsS0XytKQU4AnLa",
    "4qDpLaFGf5ampf2DXD2TMA",
    "4z2rdFGA0G1JZ91cHdm2KS",
    "5wdAiwQ6QsqH6tHWcE76qM",
    "29P8nJQ6MUwRVem4d2GvSD",
    "5hkRkPXBLgstXExcsxUBDd",
    "4sjty8PrUy3ut5xT8CRg2t",
    "7qIfHNb4p0Cc4fOh3BFdWe",
    "60mrGpCA4OIUuRLwi4T5Nm",
    "2FYGZDfsAnNsrm1gVbyKnG",
    "5pv6HjEYIghenyE7K2ghyv",
    "6f1oG9hTx3NETgV6q4rkw5",
    "0mzLT53JPWyBrPLPcgjFy6",
    "0BalWDSJ7mtpiyplzQ9v6X",
    "4pspYVQGFHLPEFgQPD1J7e",
    "0ldqUhgUHeaZcaosF7RsrZ",
    "78XfOXpUShe7mFwhjBEd94",
    "2LEKRaTRb4zrsZwf2ei43e",
    "1pmyTzRjcz1qAowK5jYEEd",
    "6rLcuUaXfiHnzqeTt6eqsk",
    "5iNL1Q8iWNaQnfvur9CAaz",
    "3hXZ4wrQFg8xD4EYLJ6bTe",
    "57p8CBvPOxrvyCbn6ttl5r",
    "5sUYrNRxyAf8pen42uS1aM",
    "4nsieT9XiaZk8LGK62TjT8",
    "51bwChuoablcgmmSjvwe8Y",
    "0gcPFlSLjkVqz84RcDhyJk",
    "3eZIOFiSiaSytN3L42rLd9",
    "1cTu1MiLR4rOyzIzZd6GYP",
    "17rR9fMC2pavzgAwCLwBeX",
    "2Rgz3BdGJZtXsusCyxYdfU",
    "31NMPKiV62GtlNdvXkMNzV",
    "2t8yVaLvJ0RenpXUIAC52d",
    "4wfDTyTss4m46JBv2oXHKl",
    "6NPa1pEvBzztplwVijzTP9",
    "0qnqsfFYgBo0sPHM2JmfTq",
    "2YrZZsYXNu449o5UhiDDXF",
    "2GQ5KZ2i1GQcvrGd0FhDAv",
    "6Dn6ZZ8TEkNU3F11lyD3Sx",
    "3qhW0ioG27ZRFbZn1diK2m",
    "2gcgwomqMF4Z92EZAPv3Ic",
    "51Fjme0JiitpyXKuyQiCDo",
    "0vABJIxyZoI2BKV3a1m1uP",
    "7DCdoJx9mCpdxcyk5CtbBM",
    "0A5eua6Ev7Cu8L0jmTdbY1",
    "0B3H6se7MYo3D7BmzfvdVN",
    "12KOXptNpery3GGHVcXm6K",
    "01pBawVs9cqQgmLpOplBJF",
    "2qiNqpbZzziUVJdVe45hGg",
    "1qZMPmpD1jDcOA7gZ6TCde",
    "4VzlTUtNc2qTdMw0lXVfFY",
    "60NupHAR0J54haO984RG5t",
    "3b0QC5Dd1TOWoUVQplPSdM",
    "1ucn3B55IQQcQ8PPHcFtDS",
    "36ZvYgWivlGx3G11YXReLL",
    "1DwBNyyKnoPrQgPqY8HHRR",
    "0WhTN2qunw2aYr9nDfqw6e",
    "3MnO4NzyGKxgJyoTYB1FMQ",
    "2uYtnyuzS6QtR2HYmyDqaD",
    "5MpbgwPLN8b3M7yJvwiQ4g",
    "7lPN2DXiMsVn7XUKtOW1CS",
    "2ZqK9n82FWXPzEdBtNhEoR",
    "5hKffhqHma1j7ijxfTj3ps",
    "6uVoYP4sWcJzWOBnRNrYlY",
    "68259QF2vdPWB3zu9YE6Ol",
    "1jCRPdDQvCA5kQXtrPFWPC",
    "3bo6O0oUgrE3V2wqdzQKuE",
    "3kpYJjvM8Ja6btr5hEJLWc",
    "0MAz9ic5HYosDQIjdKUDjX",
    "2zVJlAEB0ublkqJMIn43AE",
    "1AcoISuZA2tq5uFOwRA7yu",
    "4dIcKMAuL0Bi6EcCetjaTd",
    "4tknhO5RmXIxnpoipMKBmG",
    "5jQI2r1RdgtuT8S3iG8zFC",
    "5BEkEUIQfXc7VTKQ3Y0yKM",
    "2vd2HEhrkafOi2uveHjzzh",
    "6vFjgISjK4fwJYPnMt8zAX",
    "127QTOFJsJQp5LbJbu3A1y",
    "7DC0O3pMpDFefdk51dr7pU",
    "0qaWEvPkts34WF68r8Dzx9",
    "0Tcy9RRWvcnqepvmVcqv05",
    "7l3E7lcozEodtVsSTCkcaA",
    "5Jcj1NH8m0mcV5rxfcnrUI",
    "7e6Ml0HrI55xPTfI7cVJK1",
    "1OcDoQaHG1UfDEf5ykzBH0",
    "65krG6c3veTz66mIdSU16f",
    "7rkw4KLPuxAtBHiDiUZDgQ",
    "78QR3Wp35dqAhFEc2qAGjE",
    "6RdQfx0t3ibugpvLV3Kr21",
    "5T490vvoFNU6psep0NPmxs",
    "4gphxUgq0JSFv2BCLhNDiE",
    "6ZzItbgnMdQ0cKFy4lFV7A",
    "7zUq59EhZuNeAjlHhzaGmB",
    "4yhz0mDvpYrvpNYTcvyfzW",
    "2MHCiOohBZEQuLgDTPvSzF",
    "2FPVYeyKBKSNUUKrg4L0rk",
    "3jKucb0CVbI66ilDMcDwiI",
    "4TQxGBi80EZbm6COxwIcGR",
    "69CrOS7vEHIrhC2ILyEi0s",
    "4cQf5VkpbEd10700lRrHR2",
    "3hTViUNS6M355PFX07MWyJ",
    "0nbN9YtAXrUEsAnnA9LtAG",
    "5x8WLOxPH0xpOlwZu7DFtd",
    "1CLU9Dv75foPZSBvdXyWnD",
    "0JhKJg5ejeQ8jq89UQtnw8",
    "0xCdQ9jYFDENkE2ck73CAc",
    "6BnaBFeF53LtcXpCiOWLE5",
    "16IzQG34ibAkYP02GpK6rY",
    "4ppTAJUbNXELZcoUaL90wo",
    "022bp5oecOlSvWC6Y79P8X",
    "3tGXyqBOXkjyo3Khr5oX6d",
    "2WW3PfGHh0aA2xCAyK6X1J",
    "4hArxLcGoeEMYHzqfgffT4",
    "6rv93pYJSTtReQIuwcCYvm",
    "6wo37KVqFJhtuxPTpLCcfe",
    "5u6vkDnOyaf8LsteDAj2ub",
    "01dqWNKgM2ujxu7HacaQwI",
    "2FC4hTAtJv26DjSYclg2m2",
    "7sO5G9EABYOXQKNPNiE9NR",
    "2wvLtM25eMpHK7hkidqte2",
    "0LMpXvC8a7rYNaxNCxXl3p",
    "3MoUZEDkD3ev41wp1pM9PW",
    "2KnOz4On4UakMbBYlfPa9K",
    "0lMrWcrVXHPEuVBuc0nRzZ",
    "2eemPFHIpC4Leycb1wLCbM",
    "0tBbt8CrmxbjRP0pueQkyU",
    "0mCzRKDnu4ptPxnG28Gowz",
    "214h7kR7uNssAoU5AbcaIS",
    "7KY4hAPXXg9aeYczem8JBo",
    "0uK2d3mNUFE2iSLWBEE138",
    "6C8s1ftL1nCyMX03qBRGP7",
    "4HcmKnUwCKsloslonqMzCN",
    "1CUVN2kn7mW5FjkqXTR2W1",
    "7AEvaz0EOmlqN27o6zpt3k",
    "1hJZvoGEYJAggWTWSPEzVu",
    "7nYHky4MsYG8Ts0QatLcno",
    "1T4U8Q2DRfs6OUg8DEsRZf",
    "7fwcAd0OkMVK3q184Psy0y",
    "4CtzawO3C97B0fLNawWvvr",
    "445BHCmPuybHlP31HLoDn4",
    "4onEuQRcjD1d1ajhCP4IWt",
    "3Oiauiojgokw9vWQvFmEoI",
    "70Qlewy7XO46zijMHSjbOG",
    "4zN21mbAuaD0WqtmaTZZeP",
    "3QjCmtOcE0GoiExw1XXcjw",
    "5XVjNRubJUW0iPhhSWpLCj",
    "56g8IXvGirzACIT4kLoOK3",
    "1wlRpsDjCIgfgKYEdoTOMt",
    "3SSzqNGH8gRHBXohGx7BcV",
    "5xdVqHtFS0eLuNp4Z8Wbpa",
    "5xL84TYVoMCJZc3ZIv50x4",
    "6ReKqMH5MF0dPViZh2S9L4",
    "54fohuXf4bBZwpyDDzCOYI",
    "5l4Zw9cyf5dyZGx4nhZNgP",
    "2vIkEXi009Hxc1K3oMsLqR",
    "24YEb26otbWRU3BApxqGGo",
    "0v9AdU2DkZTwqO4tm4e2q1",
    "05bArpM2cVvDXOSr3sWFxK",
    "2ZfwDVRBnEn5S3ogwv9GTN",
    "2onflYj7jOkotHJwwyJpJA",
    "2lniYUfW65zx1QljPNMD8R",
    "58Xx6ZPFsi6bqkFFZe0GD0",
    "1yUxbaoTMvKzHqGHEiRuY7",
    "1OWohya3ZfzajbCuSk59WD",
    "5Nz2BnJroLw1HPDeynxWGx",
    "26o5XzVdOn44rdDoNPbMyJ",
    "0y60itmpH0aPKsFiGxmtnh",
    "6sevrJJhfykYWlXPnPs6tI",
    "4du4QxkTVD2thsAQ6e5whY",
    "4hOiIZ407GNrHzIBVDbQ60",
    "6uzNS768MV2oDAeR6cwDZi",
    "55mCsKCo4bPuYtZvHppp8z",
    "0FYUTxJZvvOVLopuhusqYC",
    "7Bmrq5s4RGSi2ghMe7St6U",
    "6YIduwRZvUKZiN9Al7OkHx",
    "4vK4hGPmn82dIvbfwhOFaN",
    "334XlfPjfSIUWmC7STOFdT",
    "1IAeNWzRIkbkwoDS4gAvF6",
    "2vdYgWL21GkeqLPz7oZi18",
    "6MOuSpP9XTlr6obvO7d0BP",
    "04zrPERrSO4CfyargthKJ9",
    "2Tk5B1h58lJRsrivGg1jaE",
    "0QOSqWbludidwxUiGMLv49",
    "0jCJMXEIqsHn1gZBEpoz3m",
    "5GokpIAufFJxKqkJgRtdKD",
    "2CEgGE6aESpnmtfiZwYlbV",
    "0uif0Lvh62KQ8GIFY594M7",
    "3BZGi1yUqQyCNC868AqUGG",
    "6VWkAPfYuoGtGgC9zQt5Gn",
    "5Hp4xFihdOE2dmDzxWcBFb",
    "0lwjrh66nXwlyfsHtoA0Xe",
    "61RbK6DpJQHMnW99HhVaLD",
    "0mzFgjWXLxgn9guxkLUu7f",
    "0UUNO5KYvPrnO66I6u6bKZ",
    "3LmtUmPvIHFHGpVorlQ3RN",
    "7zpTG7OfNN5ZU76Fi06oPW",
    "6QZZdQPDKvIG0Q6VTH9ycy",
    "550UGU6ngW4bVv2dnqvvI6",
    "4UAVQkAmkXZ8T9mAQDJW8C",
    "5iy9QH67HXDjgThOthkDeV",
    "0JpZ13LVuTNuCeRkOYNiVY",
    "3pAIJTNS5KW6X7iLHAUOdM",
    "0jh5NRR4gX9tsFMLFDhEmX",
    "35p9K27mJB0n3fmKHFte6O",
    "0ye0596VIK35sp52bA3zpZ",
    "34sGnIHB3ZthMvHpNX1i7e",
    "5GxZzzm83wpUBcDfkH6VPk",
    "1E3u84XwqE5mHxjdTSIodR",
    "2i5sggEOgY9dbTUdb9UJ2u",
    "5cz9A9XWyLJ6lISe5EYkRK",
    "2787InRFVF74qsf075I4iw",
    "13AsMAo6AneDj0Cspa4jks",
    "1VxQboO0KAsIm8MjSShBJv",
    "7fBv7CLKzipRk6EC6TWHOB",
    "5SLWrxfHU6QzIPdf9DA6kx",
    "0dZpw3h6KZhcHec61qwevZ",
    "6xdLJrVj4vIXwhuG8TMopk",
    "74tLlkN3rgVzRqQJgPfink",
    "6Peho1Mm2PzHZ1HjvUNpT6",
    "5W2s4S60GoNsUthU51aUb8",
    "6OMNZoxNmpoZ1Y6HptLNCi",
    "5uWXtwnfK4xvLWSqvzT8Af",
    "6qMI3Ld7UfU5fi9BjZyMzL",
    "3X5LrD9Gsv9eeJAaUW76WY",
    "0tgDQtFDQD9Q9CdBXO9pln",
    "52QMimGGnZkjTQxJQaZBQn",
    "4kLLWz7srcuLKA7Et40PQR",
    "0W4MOQ2kTOm1y7ooahgQP1",
    "7q4fVHc05vJrMFayLV9Bw6",
    "7sxA24QDCYRSEUQqEAsaKR",
    "70t7Q6AYG6ZgTYmJWcnkUM",
    "2BiCQ6UGeueijAMe8CrEvP",
    "0FElWeBRGfnF9xz7BO3IGO",
    "6y20BV5L33R8YXM0YuI38N",
    "7rji3pwPqPCUVX2flQw8Zj",
    "6Bz6Rsp8GyeK4yL7APYYX3",
    "0Wthra5bFGZm1r6YWxwtdF",
    "3QFInJAm9eyaho5vBzxInN",
    "4arqWYlOUc6KYMJxainVcE",
    "60AUuYrFbCBnPvDfofMfVF",
    "64zjna5dIuO7s9FCDXQMmI",
    "2oBlsTQn7mGUCGsXBiFM5R",
    "03SEp9sXkAOAgxJtSLuVEi",
    "7llBnNJt8cCDyWIpRmW7Gs",
    "5AyL2kgLtTWEu3qO3B9SqK",
    "5t4JIJa8s8WPlKWoFi0Qsc",
    "0D0np8Odu1PNamKfajA6AX",
    "0Nq7JtZtjHjJ2fprzzgwio",
    "3syIqcdNRjbFcWkEMRRT1d",
    "6HGpK6gWJ4Pb2pTudMrswa",
    "2UsgQKBFAgmZB39XthafA2",
    "41qkN7rkmL3VUqpoGduTrU",
    "7aIG8lh4xZmWqOoASAifHf",
    "4Fk6COKDCRgoFKQx9wzpVF",
    "7hBJCiMzo1kZzzRfGOpWwE",
    "1vO6ncg0fPrxNwV9UEIip6",
    "1OUibqAMTVgzvM4xyoEbYW",
    "7jeYu8zbwZL2ia95Sg1OCR",
    "0QKfiqpEU4h9ycPSzIFwYe",
    "0YHL0wDP6b7ov6h0yEhorO",
    "4NZrZgrRoR4GwR7flWOXRI",
    "6nDKrPlXdpomGBgAlO7UdP",
    "6srThv0baveLRq4do7nRGB",
    "0Z6tfDqVIaptfkvTlKPQeW",
    "49gc8nkswHzuOS4oHFCNL4",
    "6L9MEt3jxtcsCxuWmaL9uO",
    "7lasnCbccVFUVe5zLgOXJ7",
    "65ZGrd2jF1qIzpYyCmiyWQ",
    "0SSeiqgsSOVIOvMM8ZccRP",
    "0kELHMzyLThrJN1ZJetQDB",
    "49uT6cp7GWk8GKnGOdPA1Q",
    "7C9oofAfVRvMVkke6e8S2O",
    "2yCo1OjpZARjOSfHaistBa",
    "4SjVeeMTqstUNp2VmtMzXm",
    "4VdHK58HuiYEnWor64LTUH",
    "15sj0ViWGJTdXnkF1iTTAV",
    "5bS6VIBCYdi9QL9T1upn3G",
    "46hVih7KosdGBHX4GqGys4",
    "70P4GBt2edh1TNJBWCgRM6",
    "6LuAtG9sa0aU8GTMd9CQnO",
    "4hNqe5orQdAJJ1BExZQ150",
    "647UGNmkDjdhaL6q75dXLb",
    "76nqCfJOcFFWBJN32PAksn",
    "4877aUM6Fw9gCk2EWh1Pyf",
    "4RlvVD12qVbxezDxLOkFCh",
    "0dAfw35k2hBsnbSl74AVJF",
    "52wqMbmCqeTw37jd4zFAWr",
    "0ZVpeCq77i5ZkXWLfalueR",
    "0ojp4kT8aHcwJ8UvUp8095",
    "6ho0GyrWZN3mhi9zVRW7xi",
    "5k2ibdfJyyujLQtfapR3F5",
    "7tSO7DrrYpiMXX3zM4b3oM",
    "4G8kDpgyrmgDiILzPIUnpe",
    "6zm3myLdhev6UuL8xOewow",
    "01Q3OyB05mLgH01fpdAMPP",
    "4FyRdmM74EfSpbgU4bno9W",
    "4N42f3TrE3gFSaEXPHr9Zp",
    "0WSa1sucoNRcEeULlZVQXj",
    "6Y9B3lMveGxG74hSxyXkTR",
    "47crMnBBovP3ErVw07kadS",
    "1xzBco0xcoJEDXktl7Jxrr",
    "6Pgkp4qUoTmJIPn7ReaGxL",
    "7M5Y2qx08PuUBNH6TyhbF9",
    "062UGvlTv8veAYsXY6wedJ",
    "3zECQWhwAEydeK9jUTPamo",
    "7mlns5RNPhmCx2Ak7rm5k7",
    "1n7omixiROWs5q6xpWiQuL",
    "4bjN59DRXFRxBE1g5ne6B1",
    "0sW7xBDLtKuGvcPxmt75CT",
    "22IGm6PYN1THrPe1jFT5u6",
    "6i5uTdapTTQ5ivwq2eLC5k",
    "1XFHbzTikXks9CsMq4v8Q3",
    "2LmlZvAmT1L0O3iPVSQWOX",
    "6Y5ltPYekRe3N9CDKNWb8h",
    "717QGTmZdkemDaCo1vQHG0",
    "4YhITuwINLCfXYB2WCXbCZ",
    "5RnV1VyekJFY636bhm2HQr",
    "6UN73IYd0hZxLi8wFPMQij",
    "715rIiTwG9jYo691npEfno",
    "0qczhh8fOxKyXqnaKouJyZ",
    "6fPoorVRF5PyhSw6G7Yg1W",
    "0xwMm40LGo5aJSKf9hzvvH",
    "7h9y8oMm1GtwYNhAPh4OOI",
    "6HGz5QhsVIs4lFgN9LcgJF",
    "6FcHrUU9NrYgkIsKpx6puC",
    "1UJawTtigLuhYRqLglCYx2",
    "1Lik0YKSRL2V9ZInJjysT5",
    "7LqjznQwfrax7MjQXmxqdQ",
    "11rsK9GDZ9UdWsxtDqnMmN",
    "74D6C1FAzVnnpfecWycjIa",
    "59jrAtgRKHrOoOeoTg8JDL",
    "2g1ukx0VolwI31t8z5vprw",
    "0tc3osMOoNMXeKmfvNvcKP",
    "5uhDGZiEyRZ3CyPQFtcqsL",
    "2EjSewEKEZShOUBwFXUrK5",
    "2xZfPZxInlDXDKc6NDts8Z",
    "7Bge1ZvrtAjR2X3XgJN7n2",
    "1WShqPmOqOWljVNxI60ZA4",
    "3Q715CWL879mPWCF9yh0S1",
    "461Fsj4bBegaoE6OfsAQRj",
    "2fm0inRUDbId46Go7RgAhu",
    "255aqjr60zsuqvu7yJPUZM",
    "6hrJoTsK52uW9dzYUedNGq",
    "3CVnbHaJrt0epbDiZ4euKI",
    "7poA10I15kvSUH6m44fQkS",
    "76I3PmbGZazzNlEwlp1y85",
    "5wqNh8EZsgdjumOFQkhgVD",
    "6iOV6z8bgJYVvmyMGix0P8",
    "7LUsIrW9BlMJs3WhXne9Ue",
    "4IagicEiWvDFBsRCvpPoih",
    "6FgthnS6GYgLuELf7uRdDz",
    "2EMexWs26lf8TyO7bjEtgE",
    "3xee23Fj4m6DVu9UrWX5Up",
    "1NpW5kyvO4XrNJ3rnfcNy3",
    "5ZrDlcxIDZyjOzHdYW1ydr",
    "3mdyi1i0w7bfe72a2GX4JX",
    "4G4patpYxsF6ovHZOX9wgR",
    "3DamFFqW32WihKkTVlwTYQ",
    "1aNUSKBe6UMyMk3pEu9ws7",
    "1lclXRkkjJs4dpBgACvMKS",
    "58HvfVOeJY7lUuCqF0m3ly",
    "7Giip1UJawrbpp4HqzFBFY",
    "1aTufp89NnAN0cyMWdLxFQ",
    "4HQwS0eDQ57zOER0fp7DoD",
    "6FM9I5cM5XsLBJZ1SicSEP",
    "1xGAcy4F06Cp5m7AebsEBV",
    "5e06WZ0jkStc8PDuh6dfhD",
    "1gpYSFGZNaTjynm0RWnzy1",
    "2u6Jm2klS4yvAlbSHlxUwI",
    "6AoG52kxfptY0QBQnjuQOe",
    "5Yu60RZFHNqEDR9HHgqn6t",
    "4XEYHjp86yaGfZOGT8CqPV",
    "5bz7w9uBpH6YKuADn8fIEq",
    "3rKCDtV8UcF0RytSiXxypc",
    "4AEn3ZPvN7cGTqIfwP2XtF",
    "2zyDZRccLzWgZrpdjuSOrs",
    "7szuecWAPwGoV1e5vGu8tl",
    "47UiEqtMQRGQ4vlCh7Lm4V",
    "1ALrTfSEogKhyzcgs8spWN",
    "39shmbIHICJ2Wxnk1fPSdz",
    "12DjymdvxzAYvBC3d5THz5",
    "71R6zJsrF3ffc3TBFHfivX",
    "6hEJvWfNOvTUhLuV1Or1of",
    "5gTiQou1Cit0HMXDC5nj0N",
    "6T3sH1EuBMijU1MHe2WFJt",
    "0YImOCkIJ2PWhCXaURCZnY",
    "0C3QADQBYFjcSeU8bY7Oex",
    "3v3Y1ltJeF1Cri6MpH8erY",
    "0J47tsoZf95YNsIHnNBo9p",
    "2WE47SEyW31qiPyBhdk1NL",
    "3XYpVQFbPkmscmxgjtlr0r",
    "3Ua0m0YmEjrMi9XErKcNiR",
    "0Ui05Ov0s4PnRc4JI3Pilg",
    "507UUx311ghfFTMSuHUeyS",
    "4Ko0kuCmsJW0HMKkQM7Xw8",
    "0RDkRLIQH2kzyysCsS6gQJ",
    "1FbdZWbUSYnYXVYGRxvelu",
    "6lbhkPbkKj6jnPTt1FelVo",
    "3KYBUZUtARIsuARqe8ia3d",
    "4J2lw1uoLmprtkdN4QEHY0",
    "6HnMViOtSLFKr7KI8846Ek",
    "7FJ5VhSlqCxWa0pMX0uDal",
    "6jc8ABfRupRa87DShTBnmh",
    "3Fb4cttE912XgIeD25rXRn",
    "47UnzjxpWvJKCverxM1OaS",
    "5lWSa1rmuSL6OBPOnkAqoa",
    "2NlsAcYlLgkDhnhA9Sx6HA",
    "2aQpISWUBToaF84DDiTeRV",
    "51y77e9Z0oQOr2Tzhmc6Ih",
    "1kwHrBWAlucOE57lWugotk",
    "0nfQguNoAfKFjsQHr6qnxc",
    "10nTs74T7xj4f4jzihU9ug",
    "0G0WC5ghZRRH6LJNNXtK1W",
    "3LlmKSHR3Rs0Y3KHQLAYDk",
    "43IWqSUbgHujwQ6YFGVPth",
    "654nQX5qMDEfIQQhJGW4y4",
    "1zfwRnoVXbLMQLgty1aRVy",
    "4jqEGztx6fKzzoTmhPWVrc",
    "2OF5Q3JsI2gY1Pzk7jVloQ",
    "6iMAY70a8jzTLqnWZkLhBL",
    "5hcbBprSX4taWpm6DVUuWi",
    "1sgOeFTCjl8Mi2bLZOMqIY",
    "1Wcr8zrKqbUX0zwN8Dbr16",
    "47AKrHrVUa5XAhhjVc2Kt2",
    "1p0NUnnK8cEzHwX0N8RhjC",
    "08LKVScHdTYS9LfwWohVgR",
    "2SLEZrKKVNpOXQJN8UKSxC",
    "3aQem4jVGdhtg116TmJnHz",
    "5ypiGNhYY1GUoVB1kVZmc8",
    "1R4KCEwucJLsVk5L9o250Y",
    "1hro0fz6xQAlh5a9SKg9sv",
    "2iJuuzV8P9Yz0VSurttIV5",
    "6hI3PnULFXwkOQSHLHNfOO",
    "6bLopGnirdrilrpdVB6Um1",
    "15JXQwQUL9DDqDbMmNo72i",
    "4QjqoXofFhxePyAAlTPgfS",
    "6cx36EDQVLPcmIqicRFFXW",
    "3MbCPBMZzFMPa1vMCIcgwS",
    "0n6JSldrZj5qVBnZIdZE17",
    "50Iv0gsXTFbPQnrtbkHK85",
    "16tUjfbOz2vzcOC9KlMMfz",
    "4bpQtC8zflEQJD7VFYJ868",
    "1f38Gx6xQz6r4H1jGVNBJo",
    "5sPoju3oZHg9Wq5KXxBH3a",
    "2grynUHH0A3faPhGjdkjeJ",
    "3wYEDSfFyt53dqiwlKp3eA",
    "3dfqMqfXIl61J4byZlyToa",
    "1E0kNdI3bgXpktPOgFADEY",
    "2npMfTDQAwY1Jga13HS01O",
    "2O9epVpxXB24uKsfw1322q",
    "7mitXLIMCflkhZiD34uEQI",
    "55GiOwtxNajXVbpjjIzMnD",
    "54ee5JzQCL2Lt5t0KaguUn",
    "0nbXyq5TXYPCO7pr3N8S4I",
    "0v9Ud7xm4hiYEFu5nKcYzC",
    "6ebkx7Q5tTxrCxKq4GYj0Y",
    "0aym2LBJBk9DAYuHHutrIl",
    "0LNI3jSqyyeW1gotGcA0kX",
    "7pk1VW7qa7zBQDbqMWydUD",
    "4Hk5eE7KOgdyRPmcUxFIsM",
    "5ZE5JueqE4wDi9VYqgtJxz",
    "7DnAm9FOTWE3cUvso43HhI",
    "2K30MAifix286wrrjNgG5O",
    "24l2mDpWEmA7gWgmFJ8CIG",
    "0n66u8qLBpSERUQGlh80Zt",
    "7l9bGVHuYHBD8cZkMQvpFT",
    "63wKGwzyi2oet8HF2SPqri",
    "4WoScxr3EAUBciymzCF1Nc",
    "3R42Ux087FQ5FZEIpJZL6b",
    "4dG0SlYdknf1J5qqIZwDLo",
    "65OXGbKBQ8gUyJvUd0jNpf",
    "0jGvsfWy46PKrhY07LgPAb",
    "1UJdnazAX240LtuwBA2wcY",
    "5f69wzvle0b9ColR7wuvEK",
    "4cLE8yBHEd6GjA9pTEWnbI",
    "2TerlFysDwhLHgl6FShK1l",
    "1HqRhZ7TZYP16jS71meX9x",
    "0WSEq9Ko4kFPt8yo3ICd6T",
    "15BDY6GKFfk02WaoyytP9g",
    "4QedRNEQWPPRQwwiSU18rn",
    "6OaVWaGfhXn70ZJfdVcabn",
    "0HK4ZG6dkoHgDZ3LhL2GVv",
    "3hENlPbIlUZXQ3MiosF87Q",
    "7bv4gh6n7oMtoo3qSoFXCV",
    "3Il52a6rYUkigKzA8Y0GPU",
    "7rBE9XvBL0WE9hQCXZPtD9",
    "6SCcegvQw0jvLksGAFKynp",
    "0b18g3G5spr4ZCkz7Y6Q0Q",
    "2dOlQsivPlIDjgISeoTJQw",
    "1o0xAaXY4nEaPdBGiLZdNb",
    "2TQsqJ2AN2OYqGvgCTRtSN",
    "3Dv1eDb0MEgF93GpLXlucZ",
    "6PuYSZYjpmkn7ArLHhcGv9",
    "21ahVFLZPeDQmOiIItPqkx",
    "0e1OoxrEadCErzLc0wqDVI",
    "0aWvKH7UwdzDxzDOXvFQ39",
    "07h0oYZUzlBrtTabKaDcup",
    "1qWHX5LJ8x2MEwKFElci9Q",
    "1gJbFyxVnTF8RTGCLyQxCL",
    "5zoduJ7DH7tz9QUhVvr583",
    "6SqX9J8tXk7rXaspk7GWX1",
    "1JGU71YETPJn7mYZBCtZUS",
    "5XlufuPluY6GRBlXZvnZVJ",
    "1mv4lh1rW1K6xhxhJmEezy",
    "58xJefWZNO53mXinrVO5n4",
    "30XZElqGTzvdg6clMAMcEp",
    "6KigD0mlF4VGDYiSEzAyYw",
    "0ufeCauchfjHvwhCz0XiQL",
    "3OdIiWnYRHPYtC313Z0Bwy",
    "5vdp5UmvTsnMEMESIF2Ym7",
    "3w5eRFKhjHbyG9gGbszJc6",
    "1YeWbMRfVYLBzAQBR9xUIz",
    "2KYyYELH2gzGPX1MzLHoI6",
    "0ked784BOZ1JtRVHux98jE",
    "4Oih3RDrSFg3afaOphBVuy",
    "7ygXNvPt12SwdqvIfIcXeA",
    "51Of5p3lKZeOg6itfs4og4",
    "2fSjvd4JqvqsPhKjnP21Yn",
    "69nlak3YR9ANmZQE55rYzS",
    "1VSuFS7PahCN3SWbOcQ98m",
    "46M3KFt2Aahvebp6O7zTBw",
    "4Hpib09wXgD84w4uwTPnYD",
    "4zLBcDtvYNVtF9fnG6lme3",
    "3Y6nNzWQiyS4vxdCQ5HU5y",
    "5AFrctm65wWIqJsjHPPx85",
    "5VawgLrsO34HG1sZK0abiE",
    "01c9sDv4paB121N6l2BFKY",
    "5roKV0TL5evjsTzAMZwHxg",
    "6LcauUZjF1eXQrgqMUecHX",
    "1D5XNEpnMbP4XCqScrfCPs",
    "6ra7C49NlQThNKxYk7tCpA",
    "6LIGcE4KxAI5pxsY6bkTIH",
    "2YXswOX5aKv6OHRKUcAMLQ",
    "1o3CgBrGymsxEqLYQo9Omn",
    "0bTW5Q704RHXkf57l3hRoG",
    "6g856REHXayCJOBi4VN37P",
    "6YoBe1FqFL5w10bQbemW16",
    "6wcSgeQRBNevxxWdjp8Lch",
    "0k4A0wcdZLY0OSQ1ugfi3J",
    "2ExX3amzlJ0OvDHslQwPdn",
    "6osaMSJh9NguagEDQcZaKx",
    "3eFzz6GGztSSMdz7ATiDq3",
    "5q8oybjZelukF4h0CzSUN9",
    "2lZHCWCUkxLuQ5skJhkoyS",
    "5H95n43z0KFcXGCEc0ewe1",
    "1HdRBtvG4Vdjfl8gV4vBIA",
    "25o65xKmbeuxjYSWetdNZV",
    "5mT2XzQIIciKlBadBXPMDN",
    "1kPSrfIC22Ns3nBVXVdgUy",
    "2q1sZ1iZNLQUxXciDkn44s",
    "2tld2PLZXQvA7Toq38txGT",
    "4nDGkRGsh7kZKWPFZnbqZN",
    "1t9WgS8FN0534tLBRwbaxO",
    "4xGD9C4WdFY64KWMnxjDP7",
    "5jcrFtjW9dscpbkFjjLmyH",
    "4fdupd1cxNJtzqlBsd4sew",
    "7aiClxsDWFRQ0Kzk5KI5ku",
    "44MxUoeZg6FXDlHMrSbVjX",
    "740i8saerTV8DW7dM0soCw",
    "7yIV0VpgK1u8VbAgyhuBpH",
    "7GnP4c2ZSJyoinEu0ndzWA",
    "0OyM0Z2wdidouJdqQKT4e7",
    "3kfG1doynVwyP0Hd1fsBGg",
    "43JTSkdMnBnM4GEPWtj2tN",
    "69Sy7207dnixZ6w7RSV9Kb",
    "1zo0vyy8vdtZqNfnIwZJf9",
    "5bbE0DwaHoAZDapGXmWIcw",
    "0IHSAULL6jRYaDURDyVY12",
    "3LCup59DMpM3r6fwQsZMYs",
    "6LfQ1doHkcyrH24sdP6eAk",
    "5TNbM4we0XwPGpFUrFWVms",
    "0JwCnWO80orpUCyNUXpc7W",
    "3jrDK5fX5Oj7K4RgZ5wB3s",
    "2NFWA9nqzDh4glNiNp1Stc",
    "166OeNK9VKDduSZmmqcdAC",
    "0lTljVq9gQoUSKsjfvXrzK",
    "1Wsbr1d2BouNGk2q92mIj7",
    "64YAQSR4jfmtHeJudcQix2",
    "0IFeuYP7vTwdEQf3ye0kqb",
    "0JLiYHwL8CXEysiurWmdow",
    "2KOxy7rMLZIixXLYcT3IYF",
    "2MEkDq4Rl17FXDWK5JKsVX",
    "6Dut4f8bLs70ihPVRKRp97",
    "1LZj5VdVsPURB41eMngX7S",
    "00k4IcdhoUtt3fBATrDyhh",
    "561jH07mF1jHuk7KlaeF0s",
    "68szNxXpO8OOsywNfQMDWC",
    "23ihGIrYOSzNNGJ6STAxI4",
    "2fQrGHiQOvpL9UgPvtYy6G",
    "38TlYe1miTAL6r1FyJj7PS",
    "37mG6IjvmVd0bKf83D7ZGt",
    "2KgCPRTAECwNbJG1uYdfjl",
    "6QdnKD1zwEgyOWtkrdzlOF",
    "52Zr0sinhWTCRrQhRRY4EP",
    "6djuScFQQLO2dFeu3uWegf",
    "6LFP4PIV5TY0SApw1Win8y",
    "1vTDaihmFxX2vIoraUYwkT",
    "3CZhdUrdDFo0fI1xfDjpv8",
    "35V6qXUDCvwZdmbKe5PlPG",
    "4lR1aD5lx5Y5wYxupgzupk",
    "1TQTYsynFasqExckACAoWb",
    "0uFnnurkT6KwgzfQ6KAvSi",
    "3KR76sjFdoeU9YSpZvNzwV",
    "60v5XWoyQBDRa9Kz3eYYJO",
    "40Ac876GkIU0CFljvimDpu",
    "3ZdHjM78OVjE1NvglkKOPm",
    "1E0CZWim9mfwrCkXvieES8",
    "2GwVTLKHQhTIl6KK7o8xYi",
    "0lYBSQXN6rCTvUZvg9S0lU",
    "7CCRsWADfiCJLrpUMgwxGa",
    "0WpRF4X2LyMTZnqqrXX19U",
    "0YbKNvAu6wHeM4bfRTZFT3",
    "0EDyoVqPdg9AMt8PuDeu9c",
    "5FCgroYZWzNKp3bfWutIQo",
    "2nSvBHxMZz5buzG93DM2xr",
    "1xNcBAoUw8Hz6LqK2jt4Ff",
    "7beAh9FEDhV8VUQ39fwDyf",
    "6JyuJFedEvPmdWQW0PkbGJ",
    "7fZBQnc0zXwVybgCIrQQil",
    "1KyPT1Fno54CmoGYmwi0Ix",
    "0K8tVfNLsVbYrYdNYmWqAa",
    "1uJ0AdLuYNWYfqlHl3PuGR",
    "3TP5zVqKV9GxydOXoGLdtl",
    "64UWzgxsySsNSu4LUqpJA3",
    "4EJZTeMwX31IPwAq1mctFx",
    "2zkipwaDx4fuEAEnlZUbXT",
    "5qN4HFkapdAOV94XPryVof",
    "0wH7VmJmhQKD0BC5DIGb7F",
    "63SEf6xvEI6KlEGHoeSFRD",
    "3jY1g4RkZrvrQaD98Vr7Iq",
    "7ubMyC722ICGacCfbAbz5T",
    "2sEeRKHVONJGERCwKCW2ix",
    "1oHClQEgDmmbcEx12Kc5nZ",
    "6siDDghVE7fxel5o7fE4OF",
    "3ffkbz5OvPjXjOsYTsEjKu",
    "4ToogKQq58R9TvO40qRuxi",
    "5OxveXfvga2t0se21d96Ow",
    "0YU17F0BlVXvmx5ytsR43w",
    "3M89zvwwb1jtDUDKYNsdiA",
    "0sooJd5WbNnnz5k6yO7FIQ",
    "0yHvGDYWns43XQNVhUwGcG",
    "2PqmZr6uk48GxTmvZRYjfd",
    "56urRCfhQX5H3tfGt6q3uU",
    "5r9HbvKuWfEw4SBBSekl2v",
    "63EoAM5tzp83qV0FvIad4m",
    "6GPjY7bTrvdra8MXNt6uWa",
    "38qYfuzCY66tZGiajFe4oF",
    "6EsH66Uto1zwZlDGQ6RokU",
    "4wysKuyN4GHPTRtOsbD981",
    "3p3J2slEie5sZGe3nX2ZcQ",
    "7xkQdy0cy5ymoWT7nedvLz",
    "0R05hneChwZo8O9E4A1NlB",
    "2aDPkl4GCO2b53goL5Ia4W",
    "7pDdE5FLqcNCvjxzRzm80r",
    "6IqVq76K6UuJdYwZFgXosQ",
    "0hpvdtyRJMZRMrmQvOo4aM",
    "7MiZjKawmXTsTNePyTfPyL",
    "1vByAxtr0Mzf5FtpVz9VCn",
    "20McUFi8KCIVdNDLrkTDuZ",
    "3vrm4dNThrhQ0BArrLIUOV",
    "4nJyvmSXmJ7sLX2vPKKUKq",
    "7D1Dq1oEmlKNJltvzTL0wN",
    "6YzQOngfcV0W9F8UOTnEEK",
    "6jq6rcOikCZAmjliAgAmfT",
    "0GSCAqCsmp7OVUWwC6sSgT",
    "3f6BSLU5l4emgvgIIEW59f",
    "6D4rvRXWyakmNxIPQLPnwI",
    "1o0jx46KUwABGuU4qtL3P2",
    "1HPJOoIVdUPuaebxzMrVaD",
    "6eQQLxpKeoNqwT90zSD4Em",
    "1VNLIw5MHZNyCQ7CJPcBUJ",
    "7yahqANoaeBiBRlMZQacCN",
    "7GLAZesgD4Uo91YpTiDUQ7",
    "4pH3ZfOYekw7xcROweHa66",
    "6hDMIFH7o679EYUsuWFKOH",
    "2ZomYJ3be6cfye1shw4TCd",
    "18kRiAeDDUbkHIMilpGzjG",
    "6EtaUxjbnvtcEXIbtKjSKe",
    "76A1RRDEyHKtmV3Vh6PeVN",
    "0y3XhtLCvwj7weWmVfgIPs",
    "1TwrfCc93JjAr04dXnNyLQ",
    "6JPNphYxWAYCbYbJJnkiw8",
    "18rHGxr6QDiPieSTo7cUGL",
    "3UR0xY5brbA4d8SYJEzNO3",
    "1iOiwVWx7WggyyJA00Clj9",
    "53yk9JGKI4QDmcf83Boe5L",
    "273uCXd7NPrInaiNqtkOrA",
    "6uNAgsZPuMM5InDczRkbnN",
    "6yf3MxEOScNBTYCHOAIiNQ",
    "7sn0OyaKn1XKx18JjUZkSw",
    "5BUl0EBl4tOmPtT9IN0UUP",
    "5fFEgmLAbNG75zKPn3hXOO",
    "470UJsSGp7rrMye1429V2l",
    "5VKPHVSdaazfAq41OUqx29",
    "4pbJqGIASGPr0ZpGpnWkDn",
    "3TK9qz0lTkmYH7SXL7dTV7",
    "7fHiiK6TlTzz8AMtOq7jBd",
    "7pMrfRUouoEXhpUNVOf1f3",
    "3Od03esYMrE67g4JysxvnY",
    "2ON6cCZbi7momz4JLx2jTN",
    "7bcTSW4DQfRz61E9Bq776i",
    "2RjWCcfCOMzKeRJzeoe4h6",
    "2BVUOGciUUUqOPSLtHwLGp",
    "17vGPZ5EsdvtgAOCD4FLWI",
    "41TtIaBSjKWISRzUOf4BOr",
    "60tKKSUCyuDSoQHkW5yHGM",
    "2ebQHnlofXHEDY2AZSfrxM",
    "0JX23XA8E7aN1Chj32kgVn",
    "6RUTzFmBtIl5nRpkEXiIQ5",
    "6HeKrqik6GxcbdKsk7FRnt",
    "16Of7eeW44kt0a1M0nitHM",
    "5ZzjNL4J31lqU853Un7T3f",
    "4gkKcAyrh61Hfcpj81mtH6",
    "70jyIxNr3R5k3bofVYX9GS",
    "4Li2WHPkuyCdtmokzW2007",
    "7uuo02BIR76qZ6ZXQhz7Ys",
    "4mTLnLuHoGhA2xd595OMg1",
    "1Y5nT9fZeB8BeI939pn9Tu",
    "4kXGG5keLZBauY09CO29jh",
    "4EchqUKQ3qAQuRNKmeIpnf",
    "4ZaxrHwIK1KjXT9KKvN0Ho",
    "660eekzsNZ7sdATvfIsAkR",
    "5tU8IZW99RBQLgTtQwsaz0",
    "5rFtEhBfqgE64lYU2dHpzG",
    "6ce17pZwsMcYNab5IaC5MQ",
    "4z78eVQBoMHg1e4XGp4rMj",
    "3HoOPtaBf2SmrPohseDUYJ",
    "72addOHF1Ey7PF8GKEqZpt",
    "0Bm6AncBwv1QoQyFdMRIMD",
    "0suLmBuEbatdochI4tHduq",
    "059sONalAfYqzIICi4Ti6R",
    "5hzg9p5zoHldX1O9v8qJor",
    "55IDCnfuuCn78SEC2LGfYG",
    "3jrToiaGyx4o553AfgoofP",
    "4Oun2ylbjFKMPTiaSbbCih",
    "4kWO6O1BUXcZmaxitpVUwp",
    "3twU0ngWzakD9k07Kb5eoV",
    "1SbqxemPdwGlvmirtQVkCU",
    "197kumpljRTCtPk8M4WYzu",
    "0g5EKLgdKvNlln7TNqBByK",
    "5vG6arj1VenNFvm33XTAoP",
    "3507Teuh1vj1L5eMAJj80O",
    "6sby8K3nyCL8HOhB5VQT6S",
    "0wXjzthQdMd7SZu2kNwsVC",
    "4V9T160mQPM7ffpcuOBLuw",
    "24hYr62Cz2iA3OOef8mykI",
    "2nktXo04JT8oDFxIP01mFW",
    "5vmRAlW1hZRxg5A96v0aW9",
    "4cuFo47AC1DJktQX4pfFJy",
    "54hA0ldJYyT1huGfSeOjdQ",
    "5hU55DdOI7czxGFufcsrS4",
    "6qJh1ZpDmIPJQNjXdshJaX",
    "5qFOdxS3v8Dny9T4p2CUIy",
    "1oxbYXjBpvUe0pnGpbtAQq",
    "6lg0Md3xQ7U5EYAcsnysiv",
    "2AU7w5f9NKQeMRLREZMhbV",
    "792HwhrdO3ErRKL5yRe4Ge",
    "5fbVrSxxNTwMGkHu1CZXXY",
    "4X1KLgGGfQbEo31wAwgRF8",
    "1mlk3vLtVptfxRcnx3avyH",
    "6AQjPQ0ZvGn3EUu2WoGYTM",
    "1OlNRQFvFyg0Hq0dAOju70",
    "6dHTkQYY3zdR9i9Nj0IGVW",
    "4wkQmYpAaMe41Rc3sYZ7Vz",
    "6t6XCBKjGLdgAxEIzQc33w",
    "71Cid4UeolaHRzdbmMDAVb",
    "7CDawsvEPpaeckcI5Ake0C",
    "0fy3MozJBrM858gEIo3Yec",
    "3C0nOe05EIt1390bVABLyN",
    "3gj3J1HRil2MSi32qtMoaP",
    "5dUF13o48li6A2fm73PMdi",
    "6p1jN2q9aLR6IUTgnrxLlk",
    "4gbVRS8gloEluzf0GzDOFc",
    "2grS8y9w2vVp7sDJ3RnSx9",
    "7iE1KCwyKPmfmNOxqSOODf",
    "5NJBEByGJjmMLWoDkWAFlr",
    "1t0Jmqg1pKVBbxjQFZebeR",
    "1trC8L8YpawkU553ymy2zC",
    "7KA4W4McWYRpgf0fWsJZWB",
    "11AZJufpf0EdlyGes9Jgrh",
    "0Wh6e5EkmQseBGVeJqzC9X",
    "7ubUSxg7K2vbcOBbyImj9L",
    "51yr2nGdO1U2Q1sjwq07Mk",
    "0uKDvTJgKHRupHRqZdP1ij",
    "5v4ohaDtS0FrVfRzBTwMLI",
    "6V5LMAIGNd7qMjco5JjUSa",
    "3s6aU6VTgknSuwddxqEeJa",
    "6Ht3TU2SRJWi0ZjpzO33gb",
    "1JJ46YsWSVdpYus2PcRuB7",
    "7hakBrWzzouKXpopdzq9DI",
    "5XND8aufA4UvtqAgARcjfN",
    "5EqvRNLWBnhHevkDIyCPU6",
    "4KStl2JWlATZdJo8tq0jha",
    "1bwhDrXcAtqePp8mNJ0pTe",
    "7h57XEyVb7Bg9YClUFYrOh",
    "2Pner0zYKaSPQ3YeYYXdup",
    "63aj87TQG6F3RVO5nbG2VQ",
    "4ycxTFeO4ZADJwJZaMGMYb",
    "5Mv6X2odZZzin6TuwZCJk4",
    "0eq4dBI0Z0Jbvz4DxO7SuE",
    "6Vs70VrnqYWogia4mjq9z6",
    "3BYFHjIuPv7FDj5KVxaWq7",
    "3ANOLlFFoNo3yNaxpBARV3",
    "483XiZ5o13Cc1zoWV7jGml",
    "3JU7GqkbT5S51rgCbYJ20t",
    "3JXLLE8mDMNoapN7wr9xEb",
    "4I73qZ4lfgxwr3dxQuIwwo",
    "6Y02OLR58i5p3y9jVZTurx",
    "74cvkvTVxAXCew97vBnYiy",
    "0oTz1OfuL1uoGMNI3aLEkd",
    "6h1STZjpnDs1nawwavwtD3",
    "017PF4Q3l4DBUiWoXk4OWT",
    "5xKVYMxOHB2XRLCUafFrz6",
    "1VyRpTEE3InYTwUGcjsHJm",
    "5JrXxEZniILplCdUaRSeTE",
    "5Sjuitb1BrUMx46so51a0x",
    "0L586I7ZfQewK9SYX6kp3Y",
    "2mHY0y8Gw7dtsTYHX7fjvy",
    "0M2b3w9y8lsKqm4r8cq3Sw",
    "5mukg07BmGKV3EZmyfuiLV",
    "5rb9QrpfcKFHM1EUbSIurX",
    "0qTw7kEFpNdECY7jRCg54v",
    "50Jzvocn6wJOKEO3O0vVoU",
    "5phn8UcZV39k2ieBDnGY63",
    "4VY0mJNmHmvbQzaO729eEd",
    "4BkV1l61cugb2mOnoPei2H",
    "1RJZLVGpBG9nNZiHRQSWTp",
    "40vCMTDaDwwpf7DyBlmgEj",
    "7Ea8q10umMLrB2IzEZSk6a",
    "1YF2iUHdWnbO3MWI7z5aQf",
    "5yPXV3mU7D7EDH4XEcY361",
    "6Sun0pDZ9Dg5TRF1vSy32V",
    "4e4f0d6zswn0ZzqoZ14G8M",
    "2cjPokboQDr7xI0esIgg0h",
    "5AhV1iYCYJfdz8gTaikr5L",
    "3aE27Z5DDaeTcBQjTnsUMo",
    "7KhPHo1KWoA7AMOedW5Pw1",
    "0ExPO4uOgxyF55yOpUwtJF",
    "3TnTzFTNrVEsNiPl9zCVA0",
    "7eAsZXcKoXG2u4ONQslUb1",
    "3lHSI9u83d3W5jPcvs4Mvt",
    "32Mh7kOCWmNTZgre0cGvCV",
    "6ocbgoVGwYJhOv1GgI9NsF",
    "1gRQxbfL4ULWyTosgXSbWT",
    "5J11PTk7fy9TR0TKXpVvCt",
    "5Gz9p2oDVHNHLoQOPHzaXm",
    "0JP9xo3adEtGSdUEISiszL",
    "3oXnb2kGcJY43QLItd6pPM",
    "5zwwW9Oq7ubSxoCGyW1nbY",
    "2bcYHFk3XWcPnDXYY3tdJX",
    "1q8DwZtQen5fvyB7cKbShC",
    "7x9aauaA9cu6tyfpHnqDLo",
    "2Ecb2vjbJ3PTO8CgdIp7zz",
    "5iVokrKeCN1Bje8GlgxtQU",
    "5jHilrZDaP1vJMZfdN1He3",
    "5fwSHlTEWpluwOM0Sxnh5k",
    "6T7FXSuXykeGktMLGp8WgE",
    "1uNwTT1OeDK3ycz6L96Vnp",
    "62zFEHfAYl5kdHYOivj4BC",
    "3bGGvbwbhq9kIMhHaXBdYL",
    "75vNXX9hCL0yCAbYWKBBsB",
    "7xHfguzndSR2jOpMxzqh3r",
    "3ne63mn2I1EXKi6kwpqq5X",
    "1MMmKHMfsajQKx9fusCDn4",
    "4356Typ82hUiFAynbLYbPn",
    "3rWq4OYtJ9SHvufBDTMcn0",
    "6BePGk3eCan4FqaW2X8Qy3",
    "6xhRX9UuwamINRaRgrekNb",
    "27Z3UdqvdAhtJlWBMoDjBD",
    "1saGT647yytc1I9stbjb73",
    "5HCyWlXZPP0y6Gqq8TgA20",
    "4B66dqeGbZW3iLg3vgPLDP",
    "0fX4oNGBWO3dSGUZcVdVV2",
    "3B4wb5Tj6xXfJyzfE6CEk7",
    "3p23SEF1mvTwh4IW1dIX1p",
    "2vg5YDfcWlj4eK6wPPeCyu",
    "2HafqoJbgXdtjwCOvNEF14",
    "4w8niZpiMy6qz1mntFA5uM",
    "7ipGvvE90ROUNFw7ZBXBTO",
    "5EyJ2RwbFpioLgqirBcWxU",
    "6w7Lu9g9NZQZg0HmMJk00D",
    "0r0v060GKpseOx3zxy0d2b",
    "79szetO810NULq91m4aRrh",
    "7dtL3EKSsBkRmwVoJlep5j",
    "15J54YXr8wiW7P6gj7g552",
    "2CKvhcxC6vuommXliI7CTJ",
    "4M9nOR09KJ02vD5xgMnCio",
    "1MZ2r27WC9AgCSNPySgv8B",
    "5U5Q3MbGlEc6q9NK9lMiPD",
    "3u5N55tHf7hXATSQrjBh2q",
    "1o844wI52S3TjXGBwvGcc7",
    "4Nfak8iMF4kQfQ6Pa8Z79m",
    "3iB8eciGU9vZkaDYkz7Ir9",
    "21byk9pNgBLBJ1BLU7Rxpt",
    "4BxcX3oJCDIrX1PecmLW7o",
    "1fWKRuHYT9d89wrpwALYoo",
    "0YOluL7uaDRh1R5DU7WyT8",
    "6v0lAdFF4haL8xjBIUjtOw",
    "1p0bPl4D8eayeNvWPUUwKy",
    "2e9Sa881KIjKK0y86iNZ6C",
    "2bLqfJjuC5syrsgDsZfGmn",
    "2OrDYRj6eK0mZ1whBwMJQ9",
    "1SYNgyiVRZEBhV0P4YFBk8",
    "0C79m0V3CqruSMxOvHCwt3",
    "7kn9Z4KBKjXWYbYG8ibeLo",
    "3BlmiurYuWHlz0bknfEX6i",
    "5yQdGwetz8q9nD9doFzSpF",
    "5aq9aBHUeU3yqH4MeGEc2X",
    "3G1SVODcssMmS5YM5G3tun",
    "0pPZk7X0kpZPmllfzkhqti",
    "03wMGPA6NlFsEqitZcuaG2",
    "0vK80mtYypq4dAwQelZ2Dh",
    "0ZQTZDNcryXYpU6kAe5KHS",
    "2dCVCXtqyOTj7FoJinCV1w",
    "0U0ldCRmgCqhVvD6ksG63j",
    "1lt7cGXUVit8XYPO7rTvsa",
    "2CgOd0Lj5MuvOqzqdaAXtS",
    "2mQ7KmAI8gFLH3baaDXc6o",
    "4Q4YoY9SjZiu381MEgNG8z",
    "0z6BBM8lek2dzvnuIOX1Wx",
    "48kfPzBdv8Smbd1W4HCDyP",
    "4Joy4odtE1z0AX32uWoAQn",
    "0kixFP7P1RBEDIQhIxWn2V",
    "52Tx4HfJMJegYF3JPgg4EN",
    "3fjmHvNc2pRcEnU5fALayi",
    "6Tx8g6DwU1zgBm2wolzmyG",
    "2LBaDBBXLzyK3iZfoEYiKF",
    "5immr6tv3NGMqMgZTKro5P",
    "39es6eQDgs2gpxFUcwaoV4",
    "205ITBXaHL5AvaGE5pqvCb",
    "6kwAbEjseqBob48jCus7Sz",
    "1MUL6DO2gVimj2YrVedubd",
    "5AZJbQwaYGHWCY53k7fO57",
    "7F6jxbcbBpQeeBStWdMLuz",
    "6ZFbXIJkuI1dVNWvzJzown",
    "1VsuSOEVhuCaybeb1rFeCM",
    "6l7PqWKsgm4NLomOE7Veou",
    "21Nr8qCTFdVNnxOo1Jqyhr",
    "3VmezKvkt5Tl8ZrmQaFIV4",
    "00At7PWydsvg7g5xgaYan9",
    "4uywuaE7slEbUPArJSxLnP",
    "02itaCXOdC54J0ISjqqFAp",
    "0Vq34fkVd7vE0wV8AofFvF",
    "6eZkpL3mozN05PmZsgMnTB",
    "7iL0Xm22JJSB210fqcPQCx",
    "3BdWIht1D3JjPm8iQohLzW",
    "0YXWgqbr4tqlUooq8jSIr6",
    "4R4gOp9ybG85RqbrY7JELc",
    "3PIFvuzwRjfQgxtr9QwlVJ",
    "6a719glhgT3WjAX8rRkmyH",
    "7eHrOOGAvXtCMRvIiRUFs5",
    "61ZM92T2zaXIVsqncThQzC",
    "6bd1Hx3rtDqOzOha6ZGHBO",
    "7mLWKRLkfrb0L53rOY1s7o",
    "4uoU9KYkJ1aKCLLlfABfiS",
    "5QY38we5AE85kkrXUrdLEC",
    "0Es6gCeG90VDzqvz6WHOQV",
    "4ih3dyFZoeTdaeJW9mPbOI",
    "0X4qq0H9KW3RxHudQp3p5u",
    "2WZ09SXfgwAdBXB0KYK6ec",
    "6qxJsumtRVws86tFWYRE5G",
    "5eISv2N1Jt2hlfawe90sBh",
    "3uJnYKR844kT7MLpm0cquz",
    "1xm2NWzXt7BcSk3oXdMtXB",
    "5zJkRl2lsuP1bD1djEodCZ",
    "6WlTmjEjCSgU9fjUCvJveT",
    "4Ljf1OUadUwVKhljld7HUU",
    "4jk00YxPtPbhvHJE9N4ddv",
    "21yo11TFsfpDtuYyCbqhZS",
    "35j3CjgBRoqLp8LsAKsQF4",
    "0O4U6fVE1TwWYhM4fKr1Fh",
    "4RJHa0uZqGV4bGyKQe2wcM",
    "0e4A9Fak1nJ7RtBD8YpoEo",
    "0IJQeY73GsMXqwA5EBzYuP",
    "6PmrBNKZIiXL9PDVYAZWIS",
    "3o3LF7sKv1ab4UDzCBYqCE",
    "5oPy1Ke4RAYIaEvqL23zVz",
    "09ouJVawz1vpR6xBzE1YoH",
    "6OoByHOzMp2PRYQrGhvaEB",
    "18P6dphVW7uRZLfhKZa9Pr",
    "0gb1J5UrTpzaU1s3nupgCd",
    "0dZWtRrzUeE8nVYSkOrL2t",
    "6MOO3hJJFrNV9ST0hmKX8X",
    "2eMwDehkIC1j68U6FA3Eiq",
    "5fFd1eHzisfov2Yq4eijDC",
    "72gzwCIiuhigAGECE7vDoT",
    "0vDJoZI2ScYkpUYrCcdGi5",
    "3bv9gEsd9pbkutJkg1kL0g",
    "0ITaSRuI0L1RNL7ZNYTTi7",
    "1L7lC4k4xMrW5HfgVnOQoj",
    "3NTt01sMBL7sb0IV3vpKLz",
    "4oT8SYcLiOAMlD3HijE4Va",
    "38BxERIFwvwAldvKhWmRCP",
    "1INSnXU6gXtusMa4iAvJp0",
    "6NJSkhkdSttb76jd3ze5E5",
    "5odlY52u43F5BjByhxg7wg",
    "7iAiKibt8pXIu22m9iXGCC",
    "57pvcUZQ4GIzI5SPuRDdYW",
    "2ndnVdR8si7CW9T8vJRHyW",
    "3EWHIBw5UYb88fOZQOTSMs",
    "0DGzkmXGT5jrqSjaJ1EyL2",
    "5zUhPJocxHvYqWSYY73zF9",
    "0COqiPhxzoWICwFCS4eZcp",
    "1H5VQuShs4qfwBXyHF0PeH",
    "6MBEjJlXQYXr8dfxDvZuoA",
    "4BNWc6VNhfANsYMeTxGw4R",
    "3Cftq8i56tpPh8mdSmiOF8",
    "6iFuQWmPqZTiEryHjps675",
    "6GPpBSeB9om7fsGqCW3b67",
    "2KGgVZkhXWKjHZLENmjapj",
    "4s9M3dNBn91LB6OZDHnjos",
    "4vzJrkfHbCGaodPA5RY5BV",
    "52jCFwQBAf04Bi8xrE8DJu",
    "1ndtFtce8tttyqn3uVRk6Q",
    "2nfqyjd0odfjWkpWgcQ7Ce",
    "4sIb34wgeE5G0XXGTrpERP",
    "2vlTTtOscWq59rZSxCJxDq",
    "2Nob0WYAEbiGy5lynRw4Xu",
    "5g6nzsOxwxdoj6sqAl0NXB",
    "2AkmdLbVKS1steeZdy8H1l",
    "7xunizragUbkPbOlfpfvNf",
    "5jSH87XxwkvxDqPiyt1TbN",
    "7LUo3H3NYUjKhTRgYnd7fC",
    "55CHeLEfn5iJ0IIkgaa4si",
    "6FggaqcdwsE4pocJ5GaWxr",
    "6IE6DtVDkPotP6rApA7a10",
    "5072hCBK3Z15qRnTEzd8fy",
    "2mkfbff7LNN4SUbZ298AvK",
    "4uhvMW7ly7tJil31YYscAN",
    "525GY0mXYnxajolwgS8Eaz",
    "4xGuK7FsXuZwHCCuNnPzbD",
    "2TH65lNHgvLxCKXM3apjxI",
    "0m9BpxJvsHlPTyQta201uF",
    "4w47S36wQGBhGg073q3nt7",
    "5uh8m2Lna0Gfk8YGqYVb6d",
    "43Six950JvEDuGdbPsBeOw",
    "0F2BxpbxH8Yc3pLub48hrb",
    "5PTR38p16nZwaZLOGJFLgc",
    "71KRJfQUDoV74q3gLJIKM9",
    "5cRDn5aGMLvWsldoRmOOz0",
    "37hwQcXxrJ00pKXb9LI1TP",
    "77uExcckxvXEpc8wY1tz3d",
    "5EhnuLMer8qAXEDwmLtyrW",
    "73nmuIBhNPu54aC6wWBxpK",
    "4Y5gx8VuShNmakYGlnrUzD",
    "6MxMqCgqmekcr0VwSU7AVH",
    "51XdcTf35rICXNAgafoQtE",
    "2a6SWs9rXmVF6ibhelRqkV",
    "2m7sL4IIG2F5UULkgjnVLx",
    "3GCdLUSnKSMJhs4Tj6CV3s",
    "4ebr5AnOETSAEA44d7WPRq",
    "7tQvWqhMRYbZpSp5NgIG4o",
    "2lXOBYnC7HANcUryoVQBio",
    "0I2J6wT9by32C4cMYiwrJb",
    "51MC8ZRDXp1brfWFiFG56Y",
    "4HaMXBKZa59l6MnyhLK6Bw",
    "2f2FszTIz3EMGeEm6pvUnW",
    "0K7GTKSoxDipAdfBzJDw2s",
    "6jEZLz3YpnEBRpVkv35AmP",
    "6vjymPak0JRQC2P84XlI9t",
    "2evQmH8nJCkZl1pJMDFhJI",
    "7ujQ2G1nQDOb3oLtygSYdg",
    "2QqUfCa7GbxQm6gB3K4hhi",
    "6JAHfFUuqTEDT7A8eboCib",
    "0gEHrkD1MkLF3rI7iOis66",
    "0waK9D203FQO5FpMmfjxBw",
    "7eJMfftS33KTjuF7lTsMCx",
    "2Z3tg218wjSZeUI1oTSJlW",
    "4qABfS1RaGVXdBhj2BQyhO",
    "0bMbDctzMmTyK2j74j3nF3",
    "5YAtY9vhIKGZj71GYdMz96",
    "3AayefDdUFxivRs79bX7kV",
    "4NwiSwJkpBJjBBQm8dTfbS",
    "2rRJrJEo19S2J82BDsQ3F7",
    "7x9nXsowok1JszkVztI5NI",
    "0S5wIarCafLb0AOjGWJ8ni",
    "0J67SeAqemmeTxZ5K4X33E",
    "6xjjPViX3G3ygeDnuU3gab",
    "5vTtANNlQK5UhwfooDek5y",
    "2WDPXXLSTnfKzHLVpyUFp5",
    "3bT5PDBhVj4ifU11zQvGP2",
    "3nMb7ToWIxYvmaIG20z6ux",
    "7r2Ojv6e251YKARkxEg0al",
    "4LjfIjS8iweFCPdKxLnEoV",
    "09eIoXFPSIvxAmfZjIA6qG",
    "26VQvcUzPMLc1Jd8oDEbfl",
    "0blW8IbR5b6SHojx2wFH1D",
    "5qDvsmyX6iK5QId4pNePB1",
    "1uv0c8dDLoSMDlGNU2psja",
    "7ijEa6dqpBlpZ0vt71HHRM",
    "5yR26TumS74yhIOGhn8Hs8",
    "2wPc15A83OnyE9QarVRpqA",
    "3v5o91PrUtf0nmO6j8J7dZ",
    "59hBR0BCtJsfIbV9VzCVAp",
    "61s24wRVyG7NP9m7EjdDKL",
    "5Cg8AN8PU4lqR3vVTZR7ro",
    "7seIe3hB4DJjubvpL8tonZ",
    "6QWGVEHzVsD4CO2lkcUz97",
    "01dAV8cnaC8TkJKbX46Zrn",
    "7o7E1nrHWncYY7PY94gCiX",
    "3mi0BGXPmWzuaX79sds9x8",
    "32SkyVfs7k7tTsxoUjUEDa",
    "5wojyanOP6dtCtOMjcxI1i",
    "64r1Dcco8Vj0inAZgEK05a",
    "3GkkQiHQNJZ153CR7w3eFg",
    "76YbjMIB74nqaSSlmx5zLx",
    "0tFY357QKe2GKvjcWA1kxK",
    "089tprIgsyFSOrZpugamLI",
    "05BJ8vGejJnZlLGNDTn1FB",
    "78wONVlhMUDORsxQAedTbD",
    "5yR3KOac2M5tyrz4H74VfH",
    "47cKmxMxNIxXnsMPju6hdn",
    "39glqzRVRAy4vq3PqeTGb8",
    "37fPuGjPXX6hNiPkBvxTAd",
    "7ytR5pFWmSjzHJIeQkgog4",
    "4dUlSREV9ZfoogtHIcgy2e",
    "1zZ8DfrLf4fQgARxIKOs20",
    "0MX8RxbgtZWRGZRE0Z6zNS",
    "5K3SJuYEkvvrLbzOjPyRi1",
    "5wldXGLEOoRXxMWJ8rIUWE",
    "6Avndj1UPQLwR2qqzDwZBc",
    "07Z1MVkA3RNXcIwf2j9n3e",
    "00ppj2gGs8oxhGnTdejkzD",
    "2QjOHCTQ1Jl3zawyYOpxh6",
    "4kl4OmhJe0E64Y92q5mrV5",
    "70I8nlO75XOU0IPXcnT5gj",
    "28fP6qcMGPfYOjrx8AOWFn",
    "1ULdASrNy5rurl1TZfFaMP",
    "0hLgXCcfChXIcOnSSCk4Jz",
    "7azwxNpneArtcdxUv0V3vI",
    "2iI556oF2qwtac9r1RzrXo",
    "5V41HYUJcLWim5Lu4VCs88",
    "7xtDcfEszYUpo8BCIFAoQ8",
    "2EK9Ro00V92v1DU2CpcXpj",
    "7u04CdHbOv6vqsfumiHWcD",
    "1A8j067qyiNwQnZT0bzUpZ",
    "3f5y4Z2qTUmzq3JTBt3iAS",
    "5tTw4p8MlhIWmgZnhTyRZK",
    "1MMRP55jJdaT26LKJoukDE",
    "2nmcPw7xU8kavD4txEsD0R",
    "3Ue0Js6raH5eFOS3ShUxpm",
    "0IrEswfPqkHn7iGUoCDPAb",
    "30nb7NtL8QaxKSPfSVtJOj",
    "4qXKkOZ691yYgQu4Lunrds",
    "5W2QbqmtfXiz7US9DCl48l",
    "0BWbVptQRSojeI8vevbLNR",
    "7kNlRLC9PEH8nXMVawssMx",
    "44uIDpnTqjUpfweFA4lrCr",
    "5YvYKEQEYJp4orh4z3Dnpk",
    "53CJANUxooaqGOtdsBTh7O",
    "3PotQOsx243pKKnlBmq7i7",
    "1XgitgazDSMbOocH4469di",
    "2fuCquhmrzHpu5xcA1ci9x",
    "0pkduf2A27kE7xhbtGOfKi",
    "3lVoMDiuzWhYjnfU062PWJ",
    "0KBwGCY9RYD9t2zjeW4h48",
    "3gzv9P1H1OYNrSetNaEUbI",
    "7Ay1JeXkSBpZRMB6dYHc3k",
    "1Emp3xfmcBxcFt8n4srZtr",
    "0CLaGp0DMEjocSrAtvhcJl",
    "6djOXakQFRVgXcY5qVBmTh",
    "5QiNbIilmMiMBXvaAlf7lN",
    "3XF5xLJHOQQRbWya6hBp7d",
    "4uLQJx83wAjEme7NUKW8wZ",
    "2owdERQIBIIyUPCPMsb7nZ",
    "7pYfyrMNPn3wtoCyqcTVoI",
    "0pRy8BkipFAw6MnXecFXwn",
    "2nJfzBXy3xFcdqKZKZoP3P",
    "4QAUGy6k7c3IOAhgWz52r7",
    "0pkxROkC8TB5JxNY0fhVZK",
    "4IbDTrLxImTJfZePAX2nKB",
    "3XoflnowYPFRPOh3uFvHcm",
    "2aEuA8PSqLa17Y4hKPj5rr",
    "7as88HhLbDLgobaSbJrVBs",
    "23RoR84KodL5HWvUTneQ1w",
    "1CpCIb8zybdjskLQRL6rEC",
    "0TuuQ6LrSEtAkEtDDFxs4f",
    "48tv6gTp948dVjDnxYEPs3",
    "5YdnOm5990Kfq1Jodws98B",
    "3jVSV60WZE5jPE2a6KGNFy",
    "1ncjDgvOzlKXAx6RJSuWCQ",
    "68Gszh9enogLwJUbTcjjWe",
    "0KY21C9dgpwPGjNWwt8bzu",
    "4iVjDFak2Ro4FRlyRJS5qq",
    "2LEF1A8DOZ9wRYikWgVlZ8",
    "5Zpe48RJ5Vs1YuFRodYdeS",
    "2ipTMqLLogZOwB3VXafqTR",
    "6LuNP7oYy3LPslUgHtkLFj",
    "4KW1lqgSr8TKrvBII0Brf8",
    "6Mx8OezYdRyxXHXhO3j1M0",
    "3XThyUoEI8BPDjdu954Uof",
    "36KxlDMMtNyQk6PPboBXtD",
    "1TLwVV7m4TFZJrsG9qGVXh",
    "3FX5JrHUnuy5H5M7lIn8Jd",
    "6MaN3QHBcPpSRujk0uUTbS",
    "32UJQQSRSY4nH1ECcY6cPK",
    "6OTClxme7EYRZGO6An3SMc",
    "1gnKUue6F9gXXHQshCBwEs",
    "0l5fWjOl1LaY8LdGpMVAaa",
    "3BKGvcW5yqaRN7JpXcW6g2",
    "0UHeE47Px036a6hiMfUd3C",
    "2LKOHdMsL0K9KwcPRlJK2v",
    "7BXxWRoGwvz5LK2n59yCyd",
    "0hSdx0sbSmYRVJzZTuspu0",
    "3gAEAmxdP1GIjgQ3Zud2mE",
    "4U4vRo9EM6DXaLIagwbbMW",
    "3UOr59cDPUuMoQSyiLbFmw",
    "61lywMXKiITBED8Do8LQHQ",
    "15QuREDkSjbRfPMIglfvqZ",
    "4DXGYUPycPAg8sjMY5QXpC",
    "2NYBNFRybPF5kXINZ5sTVR",
    "4Gcv5SsxnQWpmOnUI19EJk",
    "2ll5WUzszERWz9M11Mc6ij",
    "4xSFbc4P9gsgbiuRTylMjq",
    "5YQoeliHU9Iz2La6pgsL9X",
    "5ezguyvNmZlAOlkRSTOu3e",
    "5QDLhrAOJJdNAmCTJ8xMyW",
    "27nfKLXSw4Mmg0JMDcke93",
    "0A8bThZCsJkxFXsNZSf31s",
    "7bUjqwgOQo1xlvouS0prY8",
    "7moGDROshDKDpuQxtQ3q4m",
    "1LiW1DpjthLqtEfBcJvyxJ",
    "6hFcBNi664Vv4TSmEVZsMc",
    "6Fnriu0MGPeYMZ6l8GkWZm",
    "15JINEqzVMv3SvJTAXAKED",
    "6ezYHltHYhuJckdCsYsRJI",
    "4E18v8nVzQCeZBAGMZOtCI",
    "416MsJxvxSKY96DCmbJIRs",
    "2Fgownn5zYk0tnIxDm4Jxx",
    "3BMOQEQ06HLKWTAFOhiJf9",
    "5uNhltpaL5Qb4n0hBGoFdl",
    "2nYpsqoAo96QFM0hHYnPRG",
    "7MysdJNLp89Xl3zoSd5bC5",
    "41WI97T0pw5R8l1BTCZDRZ",
    "4Vm2CuGPR24AHqrBOAkGdf",
    "5RIVoVdkDLEygELLCniZFr",
    "4zad2krdbpi2crulhinPRe",
    "43aIjdFCcsTGBZMRPBPKm4",
    "40NKYSkaTC4F62QbIVJ8S6",
    "1M85o2ruB9uTj68dIXj6dJ",
    "3Z8gDycWX48tv06vVRMQtg",
    "2jdGOeIjQNuPXx8rml1FkX",
    "49UcKfLR5XYUcVJ46RMo1G",
    "0mEdbdeRFQwBhN4xfyIeUM",
    "6JWBrFsMLq5tAXMhahEKWy",
    "0T5iIrXA4p5GsubkhuBIKV",
    "2MlcK8OgC5IpQz3l093YSR",
    "1bWEngw5tAF7vWByrf5Oy5",
    "7uH27oIt4a6cIFCA8ZPcyG",
    "7C1trmcQQ5n5RNy4l6ziCv",
    "5FkJHVudUByVjanCqFXRql",
    "4NGwa1Fje5V6gZVX3P3v4G",
    "1465rreDHsuWYGU4vnYJCF",
    "3AawFHorBGEDdM9ngI8ofa",
    "3dX6WDwnHwYzB5t754oB4T",
    "5mvXiroNv8swMbCaKOwuuN",
    "2Tdj4zosHNMnsL6EExsaYD",
    "3D3NGKCfd1OyWbMi7z7LLU",
    "6rkpJTBjmVmBBB8uzr7CIa",
    "02yaX0Reb1fQYIQdri4Ow8",
    "6sdvLVBHnuNjne2DS2IrJ9",
    "2SmVkuYGvlCMbiSULGXt3P",
    "6AQbmUe0Qwf5PZnt4HmTXv",
    "50y6kX6Sd8wK5lZJcyAmX0",
    "3maqY8XwtNEzFbMZymWLrD",
    "6GTxdh4FiA8XyCLFK1vvgG",
    "2LDv4GXuR2yR6n8bdBR95J",
    "77M3svAgHHCxMorrm6XFnG",
    "2GEO6M2AwxzpyfnjqsX5Pq",
    "4Tsr9ZDEcR84qnQ9sS33ff",
    "5sbooPcNgIE22DwO0VNGUJ",
    "3e7Y6sfFlIdBMJhX7wpqVO",
    "4aIQHEQtRt3LIJGelFYdeR",
    "3aQz0z86zrKjd1mcZlonxE",
    "25PVU9aowaP69bSYRBe3sj",
    "2YuKyP77pidQlkxm8PuyJj",
    "04F6BO30fVbz2KUAaeQbL7",
    "6Y4a71PrnpvzXk7emURj2u",
    "05HVzu7VRLB3f72o0UZzNf",
    "7ztm8z7TFKsqcVZ5d0x6nE",
    "03wiHg8PguSrhGKyA1e2GX",
    "1ErwCH7Cs0iDYNzf2Fz2Qf",
    "5TRFP3n7Oi64zKyqwJZTJL",
    "2IemEFiwZ3hoTmiGYlotG4",
    "5wtfQW9yxNci1dWS4bRAC5",
    "4Q6ZUid2qqoxX3GTlBLCCP",
    "2k2RPHMeyercU9PauiKNbU",
    "1FAhgGwWPej4Bl5RTsgBiI",
    "7gI6SoPMfZOdDF0LaBKtLE",
    "4Xn8smeqwlqlqyhjhi3IIK",
    "0ElsPDFFAxENlU9V0Pn1MP",
    "63S1sMFN5EfIQMYbeijwen",
    "0FjkcycxVB1Jd7mcdEDDWp",
    "7vq5i7XNFT5TUBv6OttBpo",
    "3dNqbZY3pulGlFLYJWAene",
    "6vbMS9YsX2Ab8ocqkQ2Y0G",
    "0Wv5wuenRLI3BcwgT3HPIP",
    "2ZWmmrWUgDBcPSLihBMvhg",
    "210JJAa9nJOgNa0YNrsT5g",
    "1zTXiNcayBldIaoFcljLuK",
    "3hjFNS3ZvWlyKGK9qUa5ZX",
    "7HQSxHyORPbCQ1XtgV1k1P",
    "3wWJ1PBkXw42qtgtJxyLxT",
    "75opBODhJblQgRVzd5XmyO",
    "2SAqBLGA283SUiwJ3xOUVI",
    "1ICWpJ7PKVp81pKFzAHYwT",
    "30MdAjBfVTvBCS3vID38At",
    "3S7A85bAWOd6ltk6r2ANOI",
    "1CWOfGTaDY3fCkasX11ri0",
    "1KLzcDlRXwH2BjczNn5JOS",
    "3gsOIUj1c5C0LbqMK4w8Eh",
    "5XeFesFbtLpXzIVDNQP22n",
    "2UdXXyVh95zvT1bhq0Ka7T",
    "4MLS3xVoEtru6VQM8Fp2Z4",
    "5RRpWmpLVnZPukWYaedmsa",
    "5T8EDUDqKcs6OSOwEsfqG7",
    "51uTYPdrTmfZbIMpayEAmo",
    "6s1HpDxSC5QpyDAorY90cd",
    "49lWj0w12Bh4dUahFvptQc",
    "4etXeoHiuYVxdTZltNvSuj",
    "28FvSb3EK2X2nCoUK3Hi3q",
    "6Rlf0CM4DEKOyxsxeVMq6w",
    "2S7RApTsKT0CtYojYq2cKz",
    "2SS2oPAFHFHUimjfwyoYyC",
    "3K01yfjGY0NslZrXkWVAtK",
    "0chpQTaECrCZBusarf71Ql",
    "6u7jPi22kF8CTQ3rb9DHE7",
    "5ry7zR2iPX67LOYtz5mV8L",
    "5f0TOjFP3c96TFHzKnx5ri",
    "5X33YUtOw3gJqNjwB2ehdb",
    "7dmI8Tk8o0PEN4ZUoT2Cc7",
    "3bidbhpOYeV4knp8AIu8Xn",
    "1TBrqU6j99gGtGs3eI7JmA",
    "1HmeANWuuCP6ldvGgKwTLi",
    "71lRigR1SzhVptQboeTDit",
    "3Kp2CX12syJgLsmMV9ozCm",
    "0ou367q5bmco9pZNxq80iD",
    "4XmPIbXOayY7tz92tyIxUc",
    "7kQUdVjev73xIuwu7W6YW9",
    "2E5IP0OrSc1snoi34GgxxT",
    "20r94xA0bsYNLtYSiOE6r3",
    "4F4TGsDYacEbw4PLAIyJ2e",
    "2tnVG71enUj33Ic2nFN6kZ",
    "0qwMoAstkTXlWE8lQJBRzY",
    "0yz6PylgDjlUDkOZayhwOs",
    "48nIqwRQyLtqEcGzJWykLL",
    "1iDbUIQcRyUpl1K1WPZOVW",
    "4obMuJXFa9APNiFtlQHFBh",
    "2LaT6S4HaiWAqNd4yQ4MAg",
    "2aGn7X6ixuE9P3zaykgoWM",
    "4fouWK6XVHhzl78KzQ1UjL",
    "0KplUYWdJCCFkoAc37p6V9",
    "724qpA7rv1N1pwFM18FPtd",
    "1qowUCis8gYY9KOMuy8fCi",
    "1DL0HD4ZAkLxf5SWgOzwV6",
    "2Pmz8aqad67TXz68XeJChp",
    "6EgTYGPIKWgKUf4QnJ3dr7",
    "0pouaY7VO5WbVkR3UIPGBF",
    "29d9C5TvFxo9lwhgAHvXsc",
    "3DKKhdNzpFbRlo0XaaZBLk",
    "4TnjEaWOeW0eKTKIEvJyCa",
    "7HwGFDbX9zC4R4fgFUZBrD",
    "1U5RcTfHUq0iy7FecasOXe",
    "07LCO1xsdnd1epIsqGAMz3",
    "6tCdBWL2AKhu3UMWkx1hlw",
    "79npfYK6N5RnBc1jiaoHCr",
    "49v7kRlVxnwrrJzCRxeRXl",
    "1C5yqUtB7Jafija4tJjdrb",
    "3v9eCrcYmTjYjy68TWHj5b",
    "2dOwcOp4zBnF6LiZ1yeZsH",
    "6KdqE1loutetHOOJCTt0qc",
    "3vM9GmGlJxPnFTPuBffPOD",
    "7BiT2zF9l4QdO7EVkYFOLt",
    "0dKX4AhsbGO6wVvboR52yn",
    "49FXpm0XkKcW5DQzP7XW3L",
    "4kfUw6ge9PxgCWWFVv98ue",
    "5KvEFiHjRzKsoVTAszGcVm",
    "2KlQyazkD4Ny59WrKN6kES",
    "6mCqxnyOhr4tHMbRbQL4Yn",
    "0qg6skZXy2wKs4MSKFjJHQ",
    "6NZunfz5wbY8pYeDDlJUas",
    "7FE0ThVWVTIHYKv14xlMVr",
    "2JV5OBqTMW1F6PYOGZJatP",
    "6irguvkb4LDvKBwSXc7i3r",
    "1MTKn1hOR8BcgMoXviVF4a",
    "2UZdgov32Ywqh7DnuQPkuQ",
    "1sngyHrSOexRf40ReFVXsZ",
    "61Dbz99KOpBD8aIaUZ060J",
    "0kh2cDRCWSkxACTJpKfC1W",
    "2zXKE8sdSR53RsjKECmb9z",
    "0Rww3ql3uRmzTvLOVBFlpn",
    "1JxRXmALyRWm9MuFdF1NvX",
    "0DDOhEPI2jRoy4juqa0hZQ",
    "7hC8to6t0STrRvisdW5tJp",
    "6d2cQyhS2E4ai0VuNCorFC",
    "1H1FIl7rcQezX0fglyV1Op",
    "2bCjaF7cRm53Wdq9RtkYJu",
    "07FkzikE6FuHIa8Ma7zJGc",
    "4RGfkF0nrAx99uj9bFanfs",
    "3KkXRkHbMCARz0aVfEt68P",
    "6nGeLlakfzlBcFdZXteDq7",
    "6jvwkh4Uc9ldTEnYWFwtoB",
    "6Sy9BUbgFse0n0LPA5lwy5",
    "1GJKgHn5KAAiyWvH7H0sRM",
    "0Owqozvl8CaqpF4hsHQHps",
    "0vPvo2qG9oxhhPMss3MfdH",
    "7jzOZuWgZ5gaMet9V5Ix1d",
    "6br178iaXMQcXiNqB1OzBx",
    "28Xl7T5Wsk7OSXeSBimtdw",
    "3e7sxremeOE3wTySiOhGiP",
    "6bbQrnUSNylr37nggppd7O",
    "4UvawidQRJkvBcQb01ZM3O",
    "0RLLvYBopDwooCyvnTwgYu",
    "2acCrpnHeM7XlylIU0Xczd",
    "1dt220OBbkTsYz1NLVKIaw",
    "0gtuo2bvKsqW8yiqQvvtcr",
    "30Ek6vDZ77PWTQS9HiV3xB",
    "5mqzhMuUpvnMfwNz6iepmO",
    "1KNWLV6YchpDzqxkrb7AnC",
    "1qVXfRnJLyNufjtjTXsqQa",
    "7cv28LXcjAC3GsXbUvXKbX",
    "5ZO4oQl23MyctAAyMlKUgX",
    "0NPTpdVrseb7YGggATplQn",
    "3E4a16orMZ7IVg5KzlMAMM",
    "0OlnLZY4cmQzT6ZGttvWBM",
    "79s5XnCN4TJKTVMSmOx8Ep",
    "6VSaNvPPagk4U5Skxp6XfV",
    "5Ycplzm1BPZYMQs9iMxNsB",
    "4Z6B43hnu7n5wMf59QI474",
    "5EPytADl1LUwPgOwu2ST6o",
    "5ry2OE6R2zPQFDO85XkgRb",
    "4YQPa47NDfRm61QrDWKazv",
    "0k7wmahjkn389wAZdz19Cv",
    "2beor6qrB0XJxW1CM6X9x2",
    "4gRrh9Jnypk0G3Pnyi2WKX",
    "31uHF6XnKwuOqUzYM6O2CK",
    "37gv8d0DVqXqHbgV2mDyvl",
    "4UMPPga9jtAqvZSKjxeJ29",
    "0x66nbDEEZtWx4qJdILucR",
    "3dsyqPDiWYYilRZNBxgxHE",
    "5qLiiK3hGNTt7Y7FXcWOnQ",
    "2oq7Sgj2B3gocUBRlHIvLN",
    "45Q6hkvGtzW0VUybDnQ4n8",
    "432hUIl3ISDeytYW5XBQ5h",
    "7r2iKPqJHM4hfKgHJzccQm",
    "094hn3veGBdQoy3jdvO1ul",
    "3NYCaxkggl0Hh8vQptSUvV",
    "5D2mYZuzcgjpchVY1pmTPh",
    "0pzKMdjWnQRd7SoHnhV7EO",
    "1FpVJ7HpZInE2GvhVE2TwT",
    "1UymZaSfQII4vUkz4U5btm",
    "0249SCmGhJREOyFRA0rd1n",
    "6FerN7cPPFmumTZOovwXjR",
    "6HMUOvnq6qlJQZ1gXgORqm",
    "0KPvnR1mzB6GnvS8dKt11u",
    "6WrI0LAC5M1Rw2MnX2ZvEg",
    "0pL458y4eQ7oxzgS8ykhHt",
    "6axdwbHCgU8nDBqDr9zOi4",
    "5gXersaY4fPDuCDVDTBybd",
    "7MDobIiZKLbDDibHDA1fl8",
    "5K6OTurSjbQy83ItYhOjEA",
    "3RCV7Kh3d97mRSU5rIvUxT",
    "46HNZY1i7O6jwTA7Slo2PI",
    "08bDGEzsYd9ebCc7p23X4j",
    "7ssEhls1ZYEGtBsoovkMSe",
    "1HXhiRhQhQ7RXCTMDNoxel",
    "2viJufnGlsjR1X51CEHpeg",
    "602d2gJewoiF1FivuOMMwE",
    "3Ofmpyhv5UAQ70mENzB277",
    "1XnpzbOGptRwfJhZgLbmSr",
    "5XMjXjwCkJVmk0AHm7z8IV",
    "5tf1VVWniHgryyumXyJM7w",
    "3mcgc036MyQe5fIvZ0OKOr",
    "6gJO2kZ4ovwO7nW8xFykCQ",
    "68PDydciw4W2e16wCbr9tv",
    "6QB2D8drdH4TlT3bAzARDD",
    "3HUDCgZgaY3ZVWohToy4LJ",
    "2iwKb075HoUFjyOVR8oAeI",
    "2Cd9iWfcOpGDHLz6tVA3G4",
    "3Be7CLdHZpyzsVijme39cW",
    "6v6dxApxjDlhLjDWnVFh3V",
    "1oIHWApwC79TRxOmuZHEif",
    "4Qcc2zA8DqpqpWg7aPSgaf",
    "2tajdkuQjkkg37iglbqoav",
    "6Y46tOTRhkBamosyuWa6YX",
    "6tifCCTIVBLC2TmTquYG7G",
    "1LPcVBiNDLB3TljELa22jI",
    "0qDC8eQU1swmYQrXrXlGpx",
    "1dg3qy5DjoJodawfOCgrTP",
    "3YDuFz83RCcbbR2ZZVbvcD",
    "7vtRIoGjWGl49gUSULroi8",
    "0c5v6vgT7fbXFftFpIpZcb",
    "5r3QqN3fGVmsj7CLJAJcvm",
    "3IelG5zYpWWCZIH4cqWlPV",
    "2Fl03SBHHzyYjHp7NDlDlY",
    "6S1yBzD94iAl6HvOm2Hpyp",
    "7kDFn3yEirx9QIrkHuuAyy",
    "4cuBQhxCjoXW9EX2UqeQwo",
    "7E9XQbKJbkFwcGwjSF9Qlk",
    "6MqNwVzwTAmYQKZg0yG6oP",
    "7moBzhzOYZkbr85H2igjcB",
    "0w6lsLBvhtGcqMYA7MB7r6",
    "6VWUOFXGwH1OgyPrfRONrn",
    "6wIvFp0zpLlFC1FO91bimW",
    "11wHTbYjz1ltWTzIBnHEOB",
    "6jreFSOTUAViWjKyzOC4Kg",
    "1EKWlHb9nQGs323QqGyb4U",
    "7bYZBVrnRfqeaPbhRyEvK3",
    "7cILO3S8DYpTUyjAILiSVn",
    "3HRlmZxRIxSKUEiTtMUhsj",
    "5C0ivQMxes2lWuOANhvVAm",
    "7CTTLQc0CmdjczA0Lfszpg",
    "6LHXb1sGs72iTmpSr0603b",
    "2cZrrQMjB63c0iIugYH9zS",
    "2UVUJ1fxgye8EEg0qlt9Fe",
    "3HrzGvn4cKFxKmO2pfk9tc",
    "1sWeSMifj6Z6kZyI6z3bRc",
    "5cqOmjN3auHvZlhbebzKQx",
    "3cVNlEM3YXCM2e96b9rWGh",
    "6amuHJMQe1m2lnri4bmlDV",
    "7jvrBivTkVKjaoH25guz6n",
    "3DQuOZBoQynNvu4hkUW200",
    "3PW8R9LHr6tvhdARHAqG9s",
    "2L95U6syP0bV3fkYYOzmiW",
    "1eQBEelI2NCy7AUTerX0KS",
    "16TeQ2lM9TLU9BnLDIW1P9",
    "71aoIeMlKuQdrkHljBf0nU",
    "77j9HOrxUpWcjwra9jgvio",
    "04BNQFaBlFF7WDeTb1V0AP",
    "5x6j5ieIDRCufmEVsHt0W3",
    "2U2N1Jky3VTWJkb5lRam16",
    "7cSM9gKedvd7OXoBa0rK79",
    "4wtyVaBlDmssq5sj1cwF9S",
    "3EEd6ldsPat620GVYMEhOP",
    "3svdq1Crgj8IMezbI1K6cO",
    "4gxwajArTCk4H95J2lc2iD",
    "1DhICRHKUX0MMf1nuH2Z4y",
    "16MDfDXe5v6K0yvsXlAtkE",
    "57Zcl7oKKr29qHp38dzzWi",
    "6DVZpwOZyjhPkL09b0mqtg",
    "2alc8VZAzDgdAsL2QMk3hu",
    "28qA8y1sz0FTuSapsCxNOG",
    "2G3R9XZRRl6WPf47qgaBdT",
    "4EIg7iPo8PYxxUqugqxZoD",
    "770NVMfMtuAfAH9thj3SFy",
    "0vetigm1cKD8YvB37KCSHu",
    "5HerMpAegwiAAFOIXNCxED",
    "10luKmtlbA2PO8tH3kurlJ",
    "1Vj7Fjk2epIZqU350RUJBg",
    "0tMyLBEncRtBSMX5ajmqMT",
    "07YEzr5PuDGFoavDSbcLNG",
    "3jryyyqSjBOlrAPNFVrAk1",
    "2gBQ35qqBE75t00kV221Xy",
    "7KSDLQVszXYQnvmteqMmDt",
    "4UWDgSvethiugRKFdbaiik",
    "4zcLBfpmpWJpC0Nol0nEkR",
    "3dPLcqwq2oVn8C7KOYbkXd",
    "1Oqt89VF7VM172bY8DCuB9",
    "1TmuaS1lnCUf7yCLk2hwDT",
    "2YAuuEEyRqFB7hQehNCfoP",
    "6zAiRKvAMlXHxEtyO4yxIO",
    "0JkefbVPYQZmNxVV57gFYB",
    "0tVv9FxhUjHrhF1DLsDUNH",
    "6OboXrS1zbfCmh7uDFCIQ5",
    "7sG2bWi2eDtvX9vX8yC1Gn",
    "11HLDMuPD3wh88XHw4udKO",
    "5cz0T1Q8AmpY18TDLAe2ja",
    "6eIOtSqFJNjOTa4ReEv8Cr",
    "4EWCNWgDS8707fNSZ1oaA5",
    "1gbUrCmsJchMppBeC6wL3r",
    "6S2bFHbuGQI0CSqXeEvVQq",
    "2xQlFQeMuiyOEP3hNaAyfG",
    "08EDz6781IVLc3qMn3VneT",
    "7IEALjZHC6Wmdzu9cbPyUo",
    "0FUes88MGVcpVuVjNE7TDV",
    "4Re6jPJuAZQIzOD54RxZzc",
    "6yMiMpRVMjSKUN4ClxU9i8",
    "2hgFU1JjDJ9x7qeB83kh2Q",
    "6tzD57Ui7jeiuPTpOtV1gN",
    "6lbfqpih0QilACku60pbRy",
    "38ziag7I4rieq2OzpfuCy2",
    "27GuBokZqZ72HfLYvqmJrf",
    "1rqqCSm0Qe4I9rUvWncaom",
    "4L1YNydoXxdghlcty6TCV1",
    "0sVTL9ylbsB5OAMU6KLyo7",
    "65ES1qwOB577ZnTkizMXJJ",
    "7HQEKWXO8oGMvnGSvhRK4j",
    "7nUgT8RsWAWK0JiEyKhUys",
    "47cElLEwnbplOSL5iHeu4o",
    "6FofVmsYAs2FNeOdzQJnnW",
    "4BiiDQtijdt0WdtiyIPhnO",
    "2WnWl10jDfmFHFFsQNAiAD",
    "0FcnvvYN0qkUCo79rF4xam",
    "4HCxBO8JurhkzVgdABg9Ie",
    "4iz9lGMjU1lXS51oPmUmTe",
    "4TnFANpjVwVKWzkxNzIyFH",
    "6GyFP1nfCDB8lbD2bG0Hq9",
    "5c2HadbVTsMKjja4gohEFI",
    "4QoZVMhE66MDCd0igG0hd6",
    "2QxpVhguEv67Lwlf3wwltb",
    "0A5gdlrpAuQqZ2iFgnqBFW",
    "6SrriGAtHnL1OMROo7oQNH",
    "3SS1QAGaY6x1vLknhyUfnk",
    "6jzqY97VGs6UqEhAVOuGRz",
    "0jtrpQmIdvytmMBuHjKwQT",
    "55d553uqFMy1882OvdPPvV",
    "5LjjFLhe4QChEtBCnZBn1O",
    "5M9jOReAKGZ2AttVefFjTY",
    "2gOiFualNcCa0SWoAVJpTl",
    "2vBET2pmrQqafaS6zIaYta",
    "6toQdWWc4noiOk3Eo5mVDS",
    "2NvPn4sZ45XayzytIriCAy",
    "7lhuM9WUqdThw72dCBRmQW",
    "7i5xV1jeP9mNMvq5mtaq2L",
    "5DV4ZSCqbFv74ui3ZhimXo",
    "0KSax3mYNlIm2WAY8DpoQ6",
    "4aXcsTkhBKgoHVPZz0UajV",
    "1b6r9cNpHzAYy4HvvQsNos",
    "4JrSJLnGDVVyPQQ507lEph",
    "1PW2yk9vy9UBq738C4KZP7",
    "2A0BiNS9v0RAeRR6QPY3Or",
    "2qDTVDLjK4PctCvC8Mg19x",
    "11YlX5vmquZH6OfVjRANSl",
    "0IS07LOv3gA5ZA4gFdchcA",
    "4U0itkWcuEmqf5tOHgzlMO",
    "2ZAFvQFlMzUFgc1TYKKexH",
    "1SPqHpi8LebFcCoZs2JJCX",
    "1VO8LC2PyM13d1LxE6KLSc",
    "3hY8fS0itdxlUqn18vAMJ8",
    "47VKFCX1VhjI1nnRHd6PgY",
    "3HCZQJVHcWCzo6R56gwLDh",
    "1KDP8rGuIPRxGoqmSsdXd3",
    "7x9K6J6QC7zrpkl6BsmD2I",
    "2HRNRdM9n5CvcMYkvqPpI8",
    "5Odq8ohlgIbQKMZivbWkEo",
    "1uGsQSTYHkKDTyg7f9ohlJ",
    "0auWmQ8dkRRXWTDTI6PMVz",
    "2oihnMe9zaw77zyXro3YxU",
    "1VdYuaX09Fl8wJbGKloAfA",
    "49IcXNGob9bCdmTsA46onT",
    "7eYqEC2WBB3xrsTRPSK60v",
    "30cW9fD87IgbYFl8o0lUze",
    "4lDOSp8oal2s6ViF09eoxi",
    "3NGouqhbWEjkKJFqNTFBhM",
    "6MJaRAIaYhE1LFRhuF9a3O",
    "0eWfHigLsQiQzmKRVbwjLL",
    "4Clmg1g8n2yBYG13Z1oSdG",
    "0MYLzCswPtYON4yYWmB4dx",
    "48fPdAwGVoSkGK8GSez9yx",
    "00s0HPhy1PXovEfmcDcEx6",
    "3Uyu2grOhwjhkwcXLKlWwP",
    "1qYlzlWIWRaEGF9Qjf0T2P",
    "6ikDZX0oc8EKGj2vdMAEDv",
    "73zQG7t3tZDyePEflVSqJJ",
    "3rb0tMq42WfggucPm0HHkA",
    "2ZRo7axmMPeSVUvDbGkJah",
    "7MRuRRdflGJnF2hAPk8bkr",
    "5xdowKbFi2qOKYkxB7UT3v",
    "58hjBuGWj43LQ6WjN3ZQAK",
    "0YammaEkYSeo9vQYZ1OwS6",
    "6h5PAsRni4IRlxWr6uDPTP",
    "1tyx1wJFT7wAeF1PKOOe4y",
    "3PGs6DJ2Q7vZKuRttg30Ww",
    "2LVMVLS3QG6zDhETZrMqoK",
    "79IJUGY4ELv8iMeAGYk83S",
    "7Ie9W94M7OjPoZVV216Xus",
    "5YTUCHSwfwJ4oHFDjFgpEe",
    "3sGOutwxqOQrVZnHfK1dt4",
    "6D6EjO2uEz6Ddi74wAJVyy",
    "6puWOoY5pvOoycq5RDSrO5",
    "08X1cq1aoXTfR3FPZZlkBr",
    "3tvaxLYbjhClWGvvaZQxo1",
    "4Ijr3J0lnLCGZvpXBiqCjU",
    "1KF0Cv5YvI21Idhttctsmb",
    "5bJNlffrE4PAKrBo7bjqOl",
    "4ZhPLoMzZwewHLLjV1J15c",
    "0TXLWUylDEutqkWq4lI590",
    "0DC2OR1ODB69FH1JzGFLTX",
    "4gG39gZ9S1oH6vfGvxLnPI",
    "2OlHQK9zAVHIxcwyrnQioD",
    "2JmbEZudT2eA3kUp5nXGZf",
    "36EtEIlRPhik2TCCCfWA2O",
    "4qDHt2ClApBBzDAvhNGWFd",
    "0HIj0uo7zaFIpkzUIkDlmL",
    "6BeFZcS3rJHLZnDHXIQ3rA",
    "4hyFIcZPbDM3rxLIzrskm9",
    "05qteZmJE5MqlIuowk2jY2",
    "6LuAw59JilwQieOcFW6vfe",
    "24Yi9hE78yPEbZ4kxyoXAI",
    "4T8OzVj1mcE5LNC3deHs4l",
    "6VBCChhlKn6vOYCfzzuE4q",
    "5XRvpUtk1ux7Tni2RAayDB",
    "7KhINDwLyIfcImRaqeog9r",
    "2eLx82S18Dc7rTw1X7WroJ",
    "6xIDZPcKh7x070OUZkt7Fr",
    "2HUKrhFPUxCLuCoQFw3Fat",
    "6i7zAdNhzUN2k1HcrBxPHG",
    "7pMRoGLEJuFM2wl5pt0R99",
    "6lknMmJZALXxx7emwwZWLX",
    "77ePeF9L2QKvKrSsWpJXBF",
    "2CICWQRS3AFpR4h5Nm9uqU",
    "7rPaFoaK4CjcFujFhIWMcO",
    "606LnHssjBNoQIrxa9KTYK",
    "5or3DfWwQPvoFSEKhifZaq",
    "4nrcPumLm5ozA8qOEHcVm2",
    "1953sKBpRxK9dp7jTEn4v5",
    "1N94c7T72slyq4tl2DjDqE",
    "42FUNUTTu4dhDhca834rd6",
    "0Jh6iWjna1wk5le0Ahn7No",
    "4ET0dzN5MlTYFYPCfe2RlK",
    "5XoaHIInmGuv7j6KssXWBg",
    "04IZ1PHFe3MFFleamY6vMH",
    "17u063wqiI6akPV0QMVWEq",
    "5wxYxygyHpbgv0EXZuqb9V",
    "4WxHWaW8cMpaJ3X8KlExkx",
    "4IfRmKWVPEPKseCmTCwirV",
    "5RrEwWlWO464QipEsFcInp",
    "73L8DSHOQImkA98ZkwPF7j",
    "6tFFZ3OYoHbTolG08QsuBa",
    "19gEmPjfqSZT0ulDRfjl0m",
    "3XIEWK1V9n25PS9Vb6axj5",
    "5WxVXxCMRnvxUKFq40ELwq",
    "2AUHVjR5lhg6GcztbGvRkc",
    "57kR5SniQIbsbVoIjjOUDa",
    "3p07oZZpSNdVtN93M5yIY5",
    "4ozgf0wmjwHNf3ah1sfePT",
    "4fs4MJMbe10cgpF0cvTtb8",
    "1PYwJHO8dfj112hLI4t6Sg",
    "5TohiJvbk6ZVSD2dBcuDQS",
    "4dQjd6Oo2IP3UvbXFSIvTD",
    "1DegLHuaZdLmOvhUgsNV9I",
    "6Vcxzw4ifKqYxVrp3ckpVF",
    "76x1mIsCz46excW50sehDt",
    "30Zgs7raWsyFHFxSw69Smm",
    "4hR3hQKELrARHNZJ51D14s",
    "75q0EUV88J6BFVDJ5fybko",
    "5O205yYinYk1LRxVkrnOJm",
    "4AkpDzc8p8JWbUwoCljWQo",
    "3nqQXoyQOWXiESFLlDF1hG",
    "6yr1ix2xyEAVxfgxFQlX8r",
    "5SYovWMQq0vPKMg7kzYCVy",
    "7Llqq3e3Hf4ICVJNBi2muE",
    "5LCaw96SsbpHAQFAcbFwbI",
    "0J6mQxEZnlRt9ymzFntA6z",
    "22wKQbMH8n7wZfso2VcLJL",
    "3d3dx2WnBHEYIq3j9onh0U",
    "0wnhv133EtGVRkDv2F7uWs",
    "7MAibcTli4IisCtbHKrGMh",
    "2bL2gyO6kBdLkNSkxXNh6x",
    "0lnlUETKob1HUDDtEY5bPH",
    "091NiGWv2nTM8pnOEXZR6T",
    "4d5NcfD8r5HPmGFzgXA1i3",
    "7aPzLeR6IvCQVaPM2vjcU7",
    "6izhPbUU3CeMYvTT74YHnb",
    "2rnDPE04mBt78lfmp9JNDP",
    "7oJASFzHpiA3ynM1Tq70TK",
    "1j4MPw77pRZ77fMBuaRCZl",
    "5ETofZQAgToMKCaCXE6FGF",
    "66145nIrccD0mtG8LdLkNO",
    "37r8w5vYWx3VSTpBoVgoMc",
    "3DK6m7It6Pw857FcQftMds",
    "6S8VqLOpx3ljoHWMisHJTy",
    "3ze3ouuovH0xrJbll9DKWu",
    "3ieLcaMIyl1Avm7JtHSk0d",
    "308Ir17KlNdlrbVLHWhlLe",
    "69urju2iS7zKGTxNVLYt5D",
    "15BlympuVSfZFROojEMY2M",
    "3mIJ1QVBNoEuIiTikoP0Rq",
    "1ICPREUY4yMNeFEgbNh7D5",
    "1yxcwoaLZIIReC3zG0c3je",
    "7q0UaGV37uCvkkonTrUZJc",
    "28r1xYNakXXwcQKIXu9Wjw",
    "5nIu0VwPOsjkF61zfevLKh",
    "5GIE4sOL5Dk9gLbowUtUpT",
    "0RDUfhoU2oeNZ4ILuMBDiG",
    "2BUDOrTS82npIINrWb1uXj",
    "2Fyxt0Ws62qiIn9hJWxMA9",
    "4gpKdwSyeN8MSsKa6FY4Qf",
    "1F1oSc7mdgcqZGO1zSWtWc",
    "6T3ME5ZT14N9iJdnVhlBUV",
    "5gIl8sJHIZKUQAKb8nNDdE",
    "18AJRdgUoO9EYn11N7xzaT",
    "7DtUfn3db8fLh7Nj1tiqNG",
    "0fNz515a6jKUFcriG87v7I",
    "0ow0OPJOJKhvFvWyLqcHFJ",
    "5v2G8GFDvKGnYzTop0ObSn",
    "2ZjTAieewsBC24kPGfLagc",
    "5LRjTa2Gx621pNhX0i04RU",
    "5PsLICW9HfBbHZ64TT1liT",
    "6sPwDfbYz9rGmdrKOJ5SNv",
    "37Yw0rdyHAQlXA0V1mUmKZ",
    "4TFDeBqHM6jvbqAi2DAtlv",
    "1Mze7crzF9BWo82DiAsmjj",
    "6w5VrZqwVBOByJ1ySNVWpu",
    "0OUR3m3eHEgSqxs9JxZovz",
    "3W2yQv20KEfhjPKmDo5dpK",
    "05y0oAtMDyvST8FXzBIHkf",
    "2HjbHbmr8tVQcGhYROva27",
    "3W9xukFv9kGLkLbEe2YITe",
    "25SKfrMP4XWx8yOBWr0oka",
    "7EroGeDg1uteOaQ45Ftfiz",
    "7CvOnbFdnIoXMQ4eFCo5lB",
    "6l8mgVN9Xf1hiDIFGA6CTE",
    "0P5neEBQdCW7uVm1YdxIZU",
    "14s7D4i8VWZUrRgRHp4huJ",
    "49vPDBFvOB9RKQNtzeLDay",
    "5mg3VB3Qh7jcR5kAAC4DSV",
    "1mwxrkuk4A03ysARJN7At0",
    "3lGXcDDNmusm2s6Vlr8Qy2",
    "3B54sVLJ402zGa6Xm4YGNe",
    "3cpWvdAOJaMFhFMr8V07AG",
    "2XLH1URNRufDgkk3fDm4Su",
    "3z8h0TU7ReDPLIbEnYhWZb",
    "0pMUR7Uvp6vxlbG0qBFvgM",
    "7hJQ2XawMljIJgDdbGaghU",
    "780be5fB7823aHG06mwTat",
    "23dwrzeJtEEGl2U4CPWSor",
    "5pmL3RzOy3IvGFaSDi4hZL",
    "6fTt0CH2t0mdeB2N9XFG5r",
    "4rodrZGDQp8dzSFPbrffj1",
    "0C3Y9kst8c4UmLzomWeTTw",
    "0GDVj31c8AxWXjWFzVFu0d",
    "4pCvnGkf7jveRMKHZosxxB",
    "1cn6bCfpuXuUeQaym2kgU4",
    "2WIwmd809qDTOn4UJgDnNi",
    "6ntbmkKyRh0KWCheXnBLqr",
    "1mMtql7U5OZWFUE6oVHYBk",
    "6357E8sF3frl2cadgany9z",
    "5kn2FMZoBVClbA9CV7w3k5",
    "0VJu2YKyBXyCFVE6cZaGpS",
    "4wejqH3DP6eiIqi6t3DWqJ",
    "0MwhtZx5lhT4HUey9HPwoW",
    "7G4EdFJbcn05PmDvQnSKGX",
    "1yVSHN5ndzDrTAz9UZFmas",
    "6NZtSdYMHFCrGGCQX2vom6",
    "2kHSBG2xBdKrXEc2jHyBNY",
    "0tnFKjEEsjD3AVShRgtIun",
    "5yN3wXc6fvM5SPTFjL6c4G",
    "4NEg4tcp1ZRzmr4r6ilr6U",
    "6C0p0MTrfAhTZbdy3fpnDc",
    "1JY6B9ILvmRla2IKKRZvnH",
    "4azG4CFB2tCEnfjagXSraz",
    "4o7Rszx7VVCzrCr1RPlPot",
    "1EWsVHU4FNAdtN4R8FETag",
    "7w8rpLhSxXKhHEM3iFjU9G",
    "71NOmiKvk7s5R7dUurNjuy",
    "4bmvfx88H75CcEE0mKXD3q",
    "1ra1q5ndn60WQD0LyFFoeP",
    "0WKY4nRJgz3GUG7IqkTgUH",
    "5HRlrrGBMajbttxdTJuIHt",
    "1hoHkGAvh1XHnNrLMU4sMg",
    "4P6BuLsqtg5uISdE77ypI9",
    "4dblKUfR2u2iQXCQ82awv6",
    "5bgGbSIz8gUIqAWkMjaZIh",
    "1ADGydOgtuzBNmdFpcQGLB",
    "6BlemBicuIk2xAtmpFXr9W",
    "2zgR8nO9CGCO2hVaeQH4ZL",
    "5dAtKXyrQoQW054LZqJ5dP",
    "38SKB7UfhL6Sd6Joxex5yK",
    "7FFLJknOAUirShreB17DUk",
    "2Q8fFORnsDE6I3RNvSLXSf",
    "4hnpwE6dDqkKnYRTH68h6T",
    "3Vr6lUX3ni1Z6OLvn3YkU6",
    "4VMRsbfZzd3SfQtaJ1Wpwi",
    "2zoNNEAyPK2OGDfajardlY",
    "1s9i7W8zx7Nxx78MUIsvjV",
    "51VGufKIcDTooIr4WZzegi",
    "3QnuX3lAupB2x8UcliMm17",
    "3kEeARYWq538g9DV79avgz",
    "2oo8Z2lWcHwyc1BQiwG5ms",
    "7gga4AEElumeu53PZPzLDh",
    "2Xk9gay9SqqxPOoiMVL9fQ",
    "6il0AYJmxDMRsJQMhwMYMv",
    "4qKcDkK6siZ7Jp1Jb4m0aL",
    "6gSeNnVFZMGqbZ3GSykh7Y",
    "5urLSAXw1aR5iuBykgrToo",
    "22pd8MWWZh0o8qMl5wstyb",
    "0WU4dgElEBK9cOf2cwNfaw",
    "5VLpL2ZxEBgYcoLr6hK17l",
    "31nfdEooLEq7dn3UMcIeB5",
    "5w9c2J52mkdntKOmRLeM2m",
    "6lKOsX2JpmCcOf1ja3Xu6g",
    "5ig7Zg3ULxQam70XgvYaJp",
    "0ct6r3EGTcMLPtrXHDvVjc",
    "3vwmiFOF1FNCGEFUTvTSgV",
    "1SzNNmOHqbu4OZwM0I7n7N",
    "71yCMlsD6qbD7NmNUEoVNR",
    "3EVwNrVchN0ohZAe9j03C3",
    "59ByyDNkqRGxBom9nHssxf",
    "6uRZYG0nkocu7hpoYCAAYD",
    "3hWfKBt3n7j1xqIy6LA5ve",
    "2xvYYOE1Yglm2483jqiGCz",
    "2vHOCV5YErCA8ypUwHozcA",
    "4rU33N7ZYi47dRyWVLzJod",
    "0kD9HIFg5vnLZpJIk7zjJz",
    "1GwhpgzzkJfhKI556DHlOt",
    "7HsvXvuVfJr7nAZ1hoTR23",
    "4yhGkvdYU5bi4950r80FRo",
    "06O3hxudc6V0BOuoCFSy71",
    "5aEqcblO0Z6JloFJXtxyhe",
    "6Htqsoq5u7Z4a8hqWfMRXY",
    "1aBEFbPUBkPqjpgpwIeN0W",
    "5U6FLERTCtCgLUXU4XsIf5",
    "7AVyve7cFYTd51ha5i9kE2",
    "1aEHWqvtZ1JIBUl1loQBDn",
    "4QNpBfC0zvjKqPJcyqBy9W",
    "0D2vf791CTvpxyp465Frgp",
    "4yJZP61jBhVTesHBZ0gpQn",
    "1xSDnM7YOvB3swkMWkTyNb",
    "4GCX2fSdTwaVI2e6Gai045",
    "5VkUhqfn48jacgMB3TIUTu",
    "0D9Ep8rkReNzXNK7Ux8M1P",
    "6YgBseGmSxk9s8o33HNwBq",
    "7lxryWZvTXbYhCEfrDeo2F",
    "0eabdClGMPVwX7gJ8ilNke",
    "1BocvYKP6Khn2AXOLqNmUS"
  ]
}